[{"reward": 800, "eps": 0.2009, "len": 166, "time": 9648.92, "timesteps": 399632, "cpu_memory": 9.13, "cpu_percent": 30.5, "learning_rate": 0.00025, "loss_mean": 0.17, "n_updates": 39}, {"reward": 470, "eps": 0.2005, "len": 217, "time": 9654.47, "timesteps": 399849, "cpu_memory": 9.14, "cpu_percent": 30.5, "learning_rate": 0.00025, "loss_mean": 0.17, "n_updates": 39}, {"reward": 850, "eps": 0.2001, "len": 236, "time": 9661.47, "timesteps": 400085, "cpu_memory": 9.14, "cpu_percent": 30.5, "learning_rate": 0.00025, "loss_mean": 0.18, "n_updates": 40}, {"reward": 760, "eps": 0.2, "len": 248, "time": 9667.91, "timesteps": 400333, "cpu_memory": 9.14, "cpu_percent": 30.5, "learning_rate": 0.00025, "loss_mean": 0.18, "n_updates": 40}, {"reward": 260, "eps": 0.2, "len": 97, "time": 9670.5, "timesteps": 400430, "cpu_memory": 9.14, "cpu_percent": 30.5, "learning_rate": 0.00025, "loss_mean": 0.19, "n_updates": 40}, {"reward": 520, "eps": 0.2, "len": 141, "time": 9674.1, "timesteps": 400571, "cpu_memory": 9.14, "cpu_percent": 30.5, "learning_rate": 0.00025, "loss_mean": 0.19, "n_updates": 40}, {"reward": 470, "eps": 0.2, "len": 130, "time": 9677.39, "timesteps": 400701, "cpu_memory": 9.14, "cpu_percent": 30.5, "learning_rate": 0.00025, "loss_mean": 0.16, "n_updates": 40}, {"reward": 460, "eps": 0.2, "len": 167, "time": 9681.63, "timesteps": 400868, "cpu_memory": 9.14, "cpu_percent": 30.5, "learning_rate": 0.00025, "loss_mean": 0.17, "n_updates": 40}, {"reward": 670, "eps": 0.2, "len": 157, "time": 9685.63, "timesteps": 401025, "cpu_memory": 9.14, "cpu_percent": 30.5, "learning_rate": 0.00025, "loss_mean": 0.19, "n_updates": 40}, {"reward": 680, "eps": 0.2, "len": 215, "time": 9691.07, "timesteps": 401240, "cpu_memory": 9.14, "cpu_percent": 30.5, "learning_rate": 0.00025, "loss_mean": 0.17, "n_updates": 40}, {"reward": 480, "eps": 0.2, "len": 191, "time": 9695.92, "timesteps": 401431, "cpu_memory": 9.15, "cpu_percent": 30.5, "learning_rate": 0.00025, "loss_mean": 0.17, "n_updates": 40}, {"reward": 730, "eps": 0.2, "len": 258, "time": 9702.66, "timesteps": 401689, "cpu_memory": 9.15, "cpu_percent": 30.5, "learning_rate": 0.00025, "loss_mean": 0.18, "n_updates": 40}, {"reward": 500, "eps": 0.2, "len": 175, "time": 9707.06, "timesteps": 401864, "cpu_memory": 9.15, "cpu_percent": 30.4, "learning_rate": 0.00025, "loss_mean": 0.17, "n_updates": 40}, {"reward": 500, "eps": 0.2, "len": 160, "time": 9711.14, "timesteps": 402024, "cpu_memory": 9.15, "cpu_percent": 30.4, "learning_rate": 0.00025, "loss_mean": 0.18, "n_updates": 40}, {"reward": 340, "eps": 0.2, "len": 154, "time": 9715.1, "timesteps": 402178, "cpu_memory": 9.15, "cpu_percent": 30.4, "learning_rate": 0.00025, "loss_mean": 0.18, "n_updates": 40}, {"reward": 490, "eps": 0.2, "len": 144, "time": 9718.74, "timesteps": 402322, "cpu_memory": 9.15, "cpu_percent": 30.4, "learning_rate": 0.00025, "loss_mean": 0.18, "n_updates": 40}, {"reward": 620, "eps": 0.2, "len": 163, "time": 9722.89, "timesteps": 402485, "cpu_memory": 9.15, "cpu_percent": 30.4, "learning_rate": 0.00025, "loss_mean": 0.18, "n_updates": 40}, {"reward": 750, "eps": 0.2, "len": 260, "time": 9729.52, "timesteps": 402745, "cpu_memory": 9.15, "cpu_percent": 30.5, "learning_rate": 0.00025, "loss_mean": 0.17, "n_updates": 40}, {"reward": 380, "eps": 0.2, "len": 152, "time": 9733.56, "timesteps": 402897, "cpu_memory": 9.16, "cpu_percent": 30.5, "learning_rate": 0.00025, "loss_mean": 0.17, "n_updates": 40}, {"reward": 550, "eps": 0.2, "len": 185, "time": 9738.42, "timesteps": 403082, "cpu_memory": 9.16, "cpu_percent": 30.5, "learning_rate": 0.00025, "loss_mean": 0.17, "n_updates": 40}, {"reward": 590, "eps": 0.2, "len": 176, "time": 9742.83, "timesteps": 403258, "cpu_memory": 9.16, "cpu_percent": 30.5, "learning_rate": 0.00025, "loss_mean": 0.18, "n_updates": 40}, {"reward": 540, "eps": 0.2, "len": 196, "time": 9747.77, "timesteps": 403454, "cpu_memory": 9.16, "cpu_percent": 30.5, "learning_rate": 0.00025, "loss_mean": 0.17, "n_updates": 40}, {"reward": 480, "eps": 0.2, "len": 179, "time": 9752.29, "timesteps": 403633, "cpu_memory": 9.16, "cpu_percent": 30.5, "learning_rate": 0.00025, "loss_mean": 0.18, "n_updates": 40}, {"reward": 910, "eps": 0.2, "len": 305, "time": 9760.02, "timesteps": 403938, "cpu_memory": 9.16, "cpu_percent": 30.5, "learning_rate": 0.00025, "loss_mean": 0.17, "n_updates": 40}, {"reward": 350, "eps": 0.2, "len": 104, "time": 9762.71, "timesteps": 404042, "cpu_memory": 9.16, "cpu_percent": 30.5, "learning_rate": 0.00025, "loss_mean": 0.17, "n_updates": 40}, {"reward": 830, "eps": 0.2, "len": 249, "time": 9769.04, "timesteps": 404291, "cpu_memory": 9.17, "cpu_percent": 30.5, "learning_rate": 0.00025, "loss_mean": 0.18, "n_updates": 40}, {"reward": 830, "eps": 0.2, "len": 211, "time": 9774.43, "timesteps": 404502, "cpu_memory": 9.17, "cpu_percent": 30.5, "learning_rate": 0.00025, "loss_mean": 0.17, "n_updates": 40}, {"reward": 390, "eps": 0.2, "len": 127, "time": 9777.73, "timesteps": 404629, "cpu_memory": 9.17, "cpu_percent": 30.5, "learning_rate": 0.00025, "loss_mean": 0.18, "n_updates": 40}, {"reward": 390, "eps": 0.2, "len": 147, "time": 9781.55, "timesteps": 404776, "cpu_memory": 9.17, "cpu_percent": 30.5, "learning_rate": 0.00025, "loss_mean": 0.18, "n_updates": 40}, {"reward": 640, "eps": 0.2, "len": 207, "time": 9786.85, "timesteps": 404983, "cpu_memory": 9.17, "cpu_percent": 30.5, "learning_rate": 0.00025, "loss_mean": 0.17, "n_updates": 40}, {"reward": 410, "eps": 0.2, "len": 131, "time": 9790.26, "timesteps": 405114, "cpu_memory": 9.17, "cpu_percent": 30.6, "learning_rate": 0.00025, "loss_mean": 0.17, "n_updates": 40}, {"reward": 920, "eps": 0.2, "len": 250, "time": 9796.72, "timesteps": 405364, "cpu_memory": 9.17, "cpu_percent": 30.6, "learning_rate": 0.00025, "loss_mean": 0.18, "n_updates": 40}, {"reward": 920, "eps": 0.2, "len": 257, "time": 9803.18, "timesteps": 405621, "cpu_memory": 9.17, "cpu_percent": 30.6, "learning_rate": 0.00025, "loss_mean": 0.17, "n_updates": 40}, {"reward": 410, "eps": 0.2, "len": 267, "time": 9809.87, "timesteps": 405888, "cpu_memory": 9.18, "cpu_percent": 30.6, "learning_rate": 0.00025, "loss_mean": 0.18, "n_updates": 40}, {"reward": 640, "eps": 0.2, "len": 295, "time": 9817.39, "timesteps": 406183, "cpu_memory": 9.18, "cpu_percent": 30.5, "learning_rate": 0.00025, "loss_mean": 0.18, "n_updates": 40}, {"reward": 760, "eps": 0.2, "len": 191, "time": 9822.29, "timesteps": 406374, "cpu_memory": 9.18, "cpu_percent": 30.5, "learning_rate": 0.00025, "loss_mean": 0.18, "n_updates": 40}, {"reward": 630, "eps": 0.2, "len": 197, "time": 9827.4, "timesteps": 406571, "cpu_memory": 9.18, "cpu_percent": 30.5, "learning_rate": 0.00025, "loss_mean": 0.19, "n_updates": 40}, {"reward": 570, "eps": 0.2, "len": 219, "time": 9832.89, "timesteps": 406790, "cpu_memory": 9.18, "cpu_percent": 30.5, "learning_rate": 0.00025, "loss_mean": 0.17, "n_updates": 40}, {"reward": 650, "eps": 0.2, "len": 158, "time": 9837.02, "timesteps": 406948, "cpu_memory": 9.18, "cpu_percent": 30.5, "learning_rate": 0.00025, "loss_mean": 0.17, "n_updates": 40}, {"reward": 350, "eps": 0.2, "len": 178, "time": 9841.56, "timesteps": 407126, "cpu_memory": 9.18, "cpu_percent": 30.5, "learning_rate": 0.00025, "loss_mean": 0.18, "n_updates": 40}, {"reward": 400, "eps": 0.2, "len": 143, "time": 9845.21, "timesteps": 407269, "cpu_memory": 9.19, "cpu_percent": 30.5, "learning_rate": 0.00025, "loss_mean": 0.17, "n_updates": 40}, {"reward": 630, "eps": 0.2, "len": 195, "time": 9850.13, "timesteps": 407464, "cpu_memory": 9.19, "cpu_percent": 30.5, "learning_rate": 0.00025, "loss_mean": 0.18, "n_updates": 40}, {"reward": 690, "eps": 0.2, "len": 179, "time": 9854.79, "timesteps": 407643, "cpu_memory": 9.19, "cpu_percent": 30.6, "learning_rate": 0.00025, "loss_mean": 0.18, "n_updates": 40}, {"reward": 280, "eps": 0.2, "len": 175, "time": 9859.37, "timesteps": 407818, "cpu_memory": 9.19, "cpu_percent": 30.6, "learning_rate": 0.00025, "loss_mean": 0.18, "n_updates": 40}, {"reward": 300, "eps": 0.2, "len": 124, "time": 9862.56, "timesteps": 407942, "cpu_memory": 9.19, "cpu_percent": 30.6, "learning_rate": 0.00025, "loss_mean": 0.18, "n_updates": 40}, {"reward": 360, "eps": 0.2, "len": 149, "time": 9866.35, "timesteps": 408091, "cpu_memory": 9.19, "cpu_percent": 30.6, "learning_rate": 0.00025, "loss_mean": 0.18, "n_updates": 40}, {"reward": 350, "eps": 0.2, "len": 141, "time": 9870.0, "timesteps": 408232, "cpu_memory": 9.19, "cpu_percent": 30.6, "learning_rate": 0.00025, "loss_mean": 0.18, "n_updates": 40}, {"reward": 620, "eps": 0.2, "len": 252, "time": 9876.44, "timesteps": 408484, "cpu_memory": 9.19, "cpu_percent": 30.6, "learning_rate": 0.00025, "loss_mean": 0.17, "n_updates": 40}, {"reward": 530, "eps": 0.2, "len": 207, "time": 9881.7, "timesteps": 408691, "cpu_memory": 9.2, "cpu_percent": 30.6, "learning_rate": 0.00025, "loss_mean": 0.18, "n_updates": 40}, {"reward": 220, "eps": 0.2, "len": 147, "time": 9885.63, "timesteps": 408838, "cpu_memory": 9.2, "cpu_percent": 30.6, "learning_rate": 0.00025, "loss_mean": 0.18, "n_updates": 40}, {"reward": 730, "eps": 0.2, "len": 221, "time": 9891.29, "timesteps": 409059, "cpu_memory": 9.2, "cpu_percent": 30.6, "learning_rate": 0.00025, "loss_mean": 0.18, "n_updates": 40}, {"reward": 250, "eps": 0.2, "len": 161, "time": 9895.38, "timesteps": 409220, "cpu_memory": 9.2, "cpu_percent": 30.6, "learning_rate": 0.00025, "loss_mean": 0.18, "n_updates": 40}, {"reward": 590, "eps": 0.2, "len": 180, "time": 9899.96, "timesteps": 409400, "cpu_memory": 9.2, "cpu_percent": 30.6, "learning_rate": 0.00025, "loss_mean": 0.17, "n_updates": 40}, {"reward": 490, "eps": 0.2, "len": 184, "time": 9904.64, "timesteps": 409584, "cpu_memory": 9.2, "cpu_percent": 30.6, "learning_rate": 0.00025, "loss_mean": 0.18, "n_updates": 40}, {"reward": 300, "eps": 0.2, "len": 168, "time": 9908.9, "timesteps": 409752, "cpu_memory": 9.2, "cpu_percent": 30.6, "learning_rate": 0.00025, "loss_mean": 0.17, "n_updates": 40}, {"reward": 460, "eps": 0.2, "len": 184, "time": 9913.55, "timesteps": 409936, "cpu_memory": 9.2, "cpu_percent": 30.6, "learning_rate": 0.00025, "loss_mean": 0.16, "n_updates": 40}, {"reward": 590, "eps": 0.2, "len": 152, "time": 9917.97, "timesteps": 410088, "cpu_memory": 9.21, "cpu_percent": 30.7, "learning_rate": 0.00025, "loss_mean": 0.19, "n_updates": 41}, {"reward": 540, "eps": 0.2, "len": 187, "time": 9922.7, "timesteps": 410275, "cpu_memory": 9.21, "cpu_percent": 30.7, "learning_rate": 0.00025, "loss_mean": 0.17, "n_updates": 41}, {"reward": 840, "eps": 0.2, "len": 231, "time": 9928.55, "timesteps": 410506, "cpu_memory": 9.21, "cpu_percent": 30.7, "learning_rate": 0.00025, "loss_mean": 0.16, "n_updates": 41}, {"reward": 600, "eps": 0.2, "len": 182, "time": 9933.13, "timesteps": 410688, "cpu_memory": 9.21, "cpu_percent": 30.7, "learning_rate": 0.00025, "loss_mean": 0.18, "n_updates": 41}, {"reward": 470, "eps": 0.2, "len": 133, "time": 9936.53, "timesteps": 410821, "cpu_memory": 9.21, "cpu_percent": 30.7, "learning_rate": 0.00025, "loss_mean": 0.2, "n_updates": 41}, {"reward": 400, "eps": 0.2, "len": 136, "time": 9940.0, "timesteps": 410957, "cpu_memory": 9.21, "cpu_percent": 30.7, "learning_rate": 0.00025, "loss_mean": 0.19, "n_updates": 41}, {"reward": 700, "eps": 0.2, "len": 209, "time": 9945.39, "timesteps": 411166, "cpu_memory": 9.21, "cpu_percent": 30.7, "learning_rate": 0.00025, "loss_mean": 0.18, "n_updates": 41}, {"reward": 360, "eps": 0.2, "len": 137, "time": 9949.17, "timesteps": 411303, "cpu_memory": 9.21, "cpu_percent": 30.7, "learning_rate": 0.00025, "loss_mean": 0.19, "n_updates": 41}, {"reward": 660, "eps": 0.2, "len": 239, "time": 9955.22, "timesteps": 411542, "cpu_memory": 9.22, "cpu_percent": 30.7, "learning_rate": 0.00025, "loss_mean": 0.18, "n_updates": 41}, {"reward": 780, "eps": 0.2, "len": 203, "time": 9960.4, "timesteps": 411745, "cpu_memory": 9.22, "cpu_percent": 30.7, "learning_rate": 0.00025, "loss_mean": 0.19, "n_updates": 41}, {"reward": 370, "eps": 0.2, "len": 180, "time": 9964.93, "timesteps": 411925, "cpu_memory": 9.22, "cpu_percent": 30.7, "learning_rate": 0.00025, "loss_mean": 0.19, "n_updates": 41}, {"reward": 890, "eps": 0.2, "len": 235, "time": 9970.8, "timesteps": 412160, "cpu_memory": 9.22, "cpu_percent": 30.7, "learning_rate": 0.00025, "loss_mean": 0.18, "n_updates": 41}, {"reward": 570, "eps": 0.2, "len": 146, "time": 9974.51, "timesteps": 412306, "cpu_memory": 9.22, "cpu_percent": 30.7, "learning_rate": 0.00025, "loss_mean": 0.18, "n_updates": 41}, {"reward": 470, "eps": 0.2, "len": 130, "time": 9978.02, "timesteps": 412436, "cpu_memory": 9.22, "cpu_percent": 30.7, "learning_rate": 0.00025, "loss_mean": 0.19, "n_updates": 41}, {"reward": 470, "eps": 0.2, "len": 190, "time": 9982.83, "timesteps": 412626, "cpu_memory": 9.22, "cpu_percent": 30.7, "learning_rate": 0.00025, "loss_mean": 0.18, "n_updates": 41}, {"reward": 700, "eps": 0.2, "len": 203, "time": 9988.03, "timesteps": 412829, "cpu_memory": 9.22, "cpu_percent": 30.7, "learning_rate": 0.00025, "loss_mean": 0.18, "n_updates": 41}, {"reward": 650, "eps": 0.2, "len": 220, "time": 9993.56, "timesteps": 413049, "cpu_memory": 9.23, "cpu_percent": 30.7, "learning_rate": 0.00025, "loss_mean": 0.17, "n_updates": 41}, {"reward": 450, "eps": 0.2, "len": 168, "time": 9997.86, "timesteps": 413217, "cpu_memory": 9.23, "cpu_percent": 30.7, "learning_rate": 0.00025, "loss_mean": 0.17, "n_updates": 41}, {"reward": 550, "eps": 0.2, "len": 242, "time": 10003.98, "timesteps": 413459, "cpu_memory": 9.23, "cpu_percent": 30.7, "learning_rate": 0.00025, "loss_mean": 0.18, "n_updates": 41}, {"reward": 330, "eps": 0.2, "len": 185, "time": 10008.76, "timesteps": 413644, "cpu_memory": 9.23, "cpu_percent": 30.7, "learning_rate": 0.00025, "loss_mean": 0.18, "n_updates": 41}, {"reward": 560, "eps": 0.2, "len": 204, "time": 10014.04, "timesteps": 413848, "cpu_memory": 9.23, "cpu_percent": 30.7, "learning_rate": 0.00025, "loss_mean": 0.18, "n_updates": 41}, {"reward": 570, "eps": 0.2, "len": 171, "time": 10018.36, "timesteps": 414019, "cpu_memory": 9.23, "cpu_percent": 30.7, "learning_rate": 0.00025, "loss_mean": 0.19, "n_updates": 41}, {"reward": 380, "eps": 0.2, "len": 172, "time": 10022.7, "timesteps": 414191, "cpu_memory": 9.23, "cpu_percent": 30.7, "learning_rate": 0.00025, "loss_mean": 0.18, "n_updates": 41}, {"reward": 560, "eps": 0.2, "len": 189, "time": 10027.46, "timesteps": 414380, "cpu_memory": 9.23, "cpu_percent": 30.7, "learning_rate": 0.00025, "loss_mean": 0.18, "n_updates": 41}, {"reward": 500, "eps": 0.2, "len": 162, "time": 10031.57, "timesteps": 414542, "cpu_memory": 9.24, "cpu_percent": 30.7, "learning_rate": 0.00025, "loss_mean": 0.2, "n_updates": 41}, {"reward": 390, "eps": 0.2, "len": 135, "time": 10035.14, "timesteps": 414677, "cpu_memory": 9.24, "cpu_percent": 30.7, "learning_rate": 0.00025, "loss_mean": 0.18, "n_updates": 41}, {"reward": 450, "eps": 0.2, "len": 174, "time": 10039.71, "timesteps": 414851, "cpu_memory": 9.24, "cpu_percent": 30.7, "learning_rate": 0.00025, "loss_mean": 0.19, "n_updates": 41}, {"reward": 550, "eps": 0.2, "len": 155, "time": 10043.77, "timesteps": 415006, "cpu_memory": 9.24, "cpu_percent": 30.8, "learning_rate": 0.00025, "loss_mean": 0.19, "n_updates": 41}, {"reward": 520, "eps": 0.2, "len": 198, "time": 10048.75, "timesteps": 415204, "cpu_memory": 9.24, "cpu_percent": 30.8, "learning_rate": 0.00025, "loss_mean": 0.18, "n_updates": 41}, {"reward": 850, "eps": 0.2, "len": 259, "time": 10055.3, "timesteps": 415463, "cpu_memory": 9.24, "cpu_percent": 30.8, "learning_rate": 0.00025, "loss_mean": 0.18, "n_updates": 41}, {"reward": 900, "eps": 0.2, "len": 247, "time": 10061.59, "timesteps": 415710, "cpu_memory": 9.24, "cpu_percent": 30.8, "learning_rate": 0.00025, "loss_mean": 0.18, "n_updates": 41}, {"reward": 380, "eps": 0.2, "len": 168, "time": 10065.85, "timesteps": 415878, "cpu_memory": 9.25, "cpu_percent": 30.8, "learning_rate": 0.00025, "loss_mean": 0.18, "n_updates": 41}, {"reward": 470, "eps": 0.2, "len": 249, "time": 10072.35, "timesteps": 416127, "cpu_memory": 9.25, "cpu_percent": 30.8, "learning_rate": 0.00025, "loss_mean": 0.18, "n_updates": 41}, {"reward": 630, "eps": 0.2, "len": 181, "time": 10076.96, "timesteps": 416308, "cpu_memory": 9.25, "cpu_percent": 30.8, "learning_rate": 0.00025, "loss_mean": 0.19, "n_updates": 41}, {"reward": 480, "eps": 0.2, "len": 215, "time": 10082.36, "timesteps": 416523, "cpu_memory": 9.25, "cpu_percent": 30.8, "learning_rate": 0.00025, "loss_mean": 0.19, "n_updates": 41}, {"reward": 470, "eps": 0.2, "len": 159, "time": 10086.35, "timesteps": 416682, "cpu_memory": 9.25, "cpu_percent": 30.8, "learning_rate": 0.00025, "loss_mean": 0.18, "n_updates": 41}, {"reward": 460, "eps": 0.2, "len": 131, "time": 10089.71, "timesteps": 416813, "cpu_memory": 9.25, "cpu_percent": 30.8, "learning_rate": 0.00025, "loss_mean": 0.19, "n_updates": 41}, {"reward": 170, "eps": 0.2, "len": 68, "time": 10091.45, "timesteps": 416881, "cpu_memory": 9.25, "cpu_percent": 30.8, "learning_rate": 0.00025, "loss_mean": 0.18, "n_updates": 41}, {"reward": 470, "eps": 0.2, "len": 173, "time": 10095.75, "timesteps": 417054, "cpu_memory": 9.25, "cpu_percent": 30.8, "learning_rate": 0.00025, "loss_mean": 0.19, "n_updates": 41}, {"reward": 370, "eps": 0.2, "len": 186, "time": 10100.6, "timesteps": 417240, "cpu_memory": 9.25, "cpu_percent": 30.8, "learning_rate": 0.00025, "loss_mean": 0.19, "n_updates": 41}, {"reward": 410, "eps": 0.2, "len": 198, "time": 10105.7, "timesteps": 417438, "cpu_memory": 9.26, "cpu_percent": 30.8, "learning_rate": 0.00025, "loss_mean": 0.18, "n_updates": 41}, {"reward": 90, "eps": 0.2, "len": 101, "time": 10108.34, "timesteps": 417539, "cpu_memory": 9.26, "cpu_percent": 30.8, "learning_rate": 0.00025, "loss_mean": 0.18, "n_updates": 41}, {"reward": 560, "eps": 0.2, "len": 151, "time": 10112.2, "timesteps": 417690, "cpu_memory": 9.26, "cpu_percent": 30.8, "learning_rate": 0.00025, "loss_mean": 0.18, "n_updates": 41}, {"reward": 630, "eps": 0.2, "len": 221, "time": 10117.77, "timesteps": 417911, "cpu_memory": 9.26, "cpu_percent": 30.8, "learning_rate": 0.00025, "loss_mean": 0.18, "n_updates": 41}, {"reward": 400, "eps": 0.2, "len": 144, "time": 10121.51, "timesteps": 418055, "cpu_memory": 9.26, "cpu_percent": 30.8, "learning_rate": 0.00025, "loss_mean": 0.18, "n_updates": 41}, {"reward": 850, "eps": 0.2, "len": 247, "time": 10127.76, "timesteps": 418302, "cpu_memory": 9.26, "cpu_percent": 30.8, "learning_rate": 0.00025, "loss_mean": 0.18, "n_updates": 41}, {"reward": 420, "eps": 0.2, "len": 113, "time": 10130.74, "timesteps": 418415, "cpu_memory": 9.26, "cpu_percent": 30.8, "learning_rate": 0.00025, "loss_mean": 0.18, "n_updates": 41}, {"reward": 390, "eps": 0.2, "len": 174, "time": 10135.39, "timesteps": 418589, "cpu_memory": 9.26, "cpu_percent": 30.8, "learning_rate": 0.00025, "loss_mean": 0.18, "n_updates": 41}, {"reward": 970, "eps": 0.2, "len": 326, "time": 10143.61, "timesteps": 418915, "cpu_memory": 9.27, "cpu_percent": 30.8, "learning_rate": 0.00025, "loss_mean": 0.19, "n_updates": 41}, {"reward": 260, "eps": 0.2, "len": 173, "time": 10148.0, "timesteps": 419088, "cpu_memory": 9.27, "cpu_percent": 30.8, "learning_rate": 0.00025, "loss_mean": 0.19, "n_updates": 41}, {"reward": 590, "eps": 0.2, "len": 141, "time": 10151.6, "timesteps": 419229, "cpu_memory": 9.27, "cpu_percent": 30.8, "learning_rate": 0.00025, "loss_mean": 0.19, "n_updates": 41}, {"reward": 440, "eps": 0.2, "len": 203, "time": 10156.8, "timesteps": 419432, "cpu_memory": 9.27, "cpu_percent": 30.9, "learning_rate": 0.00025, "loss_mean": 0.18, "n_updates": 41}, {"reward": 670, "eps": 0.2, "len": 158, "time": 10160.9, "timesteps": 419590, "cpu_memory": 9.27, "cpu_percent": 30.9, "learning_rate": 0.00025, "loss_mean": 0.19, "n_updates": 41}, {"reward": 310, "eps": 0.2, "len": 122, "time": 10164.03, "timesteps": 419712, "cpu_memory": 9.27, "cpu_percent": 30.9, "learning_rate": 0.00025, "loss_mean": 0.17, "n_updates": 41}, {"reward": 900, "eps": 0.2, "len": 311, "time": 10172.26, "timesteps": 420023, "cpu_memory": 9.27, "cpu_percent": 30.9, "learning_rate": 0.00025, "loss_mean": 0.18, "n_updates": 42}, {"reward": 320, "eps": 0.2, "len": 259, "time": 10178.75, "timesteps": 420282, "cpu_memory": 9.28, "cpu_percent": 30.9, "learning_rate": 0.00025, "loss_mean": 0.18, "n_updates": 42}, {"reward": 220, "eps": 0.2, "len": 131, "time": 10182.09, "timesteps": 420413, "cpu_memory": 9.28, "cpu_percent": 30.9, "learning_rate": 0.00025, "loss_mean": 0.19, "n_updates": 42}, {"reward": 580, "eps": 0.2, "len": 197, "time": 10187.18, "timesteps": 420610, "cpu_memory": 9.28, "cpu_percent": 30.9, "learning_rate": 0.00025, "loss_mean": 0.18, "n_updates": 42}, {"reward": 280, "eps": 0.2, "len": 116, "time": 10190.18, "timesteps": 420726, "cpu_memory": 9.28, "cpu_percent": 30.9, "learning_rate": 0.00025, "loss_mean": 0.19, "n_updates": 42}, {"reward": 550, "eps": 0.2, "len": 164, "time": 10194.5, "timesteps": 420890, "cpu_memory": 9.28, "cpu_percent": 30.9, "learning_rate": 0.00025, "loss_mean": 0.18, "n_updates": 42}, {"reward": 770, "eps": 0.2, "len": 206, "time": 10199.86, "timesteps": 421096, "cpu_memory": 9.28, "cpu_percent": 30.9, "learning_rate": 0.00025, "loss_mean": 0.19, "n_updates": 42}, {"reward": 640, "eps": 0.2, "len": 147, "time": 10203.58, "timesteps": 421243, "cpu_memory": 9.28, "cpu_percent": 30.9, "learning_rate": 0.00025, "loss_mean": 0.18, "n_updates": 42}, {"reward": 340, "eps": 0.2, "len": 169, "time": 10207.92, "timesteps": 421412, "cpu_memory": 9.28, "cpu_percent": 30.9, "learning_rate": 0.00025, "loss_mean": 0.19, "n_updates": 42}, {"reward": 500, "eps": 0.2, "len": 153, "time": 10211.82, "timesteps": 421565, "cpu_memory": 9.28, "cpu_percent": 30.9, "learning_rate": 0.00025, "loss_mean": 0.18, "n_updates": 42}, {"reward": 220, "eps": 0.2, "len": 166, "time": 10215.96, "timesteps": 421731, "cpu_memory": 9.29, "cpu_percent": 30.9, "learning_rate": 0.00025, "loss_mean": 0.19, "n_updates": 42}, {"reward": 680, "eps": 0.2, "len": 209, "time": 10221.27, "timesteps": 421940, "cpu_memory": 9.29, "cpu_percent": 30.9, "learning_rate": 0.00025, "loss_mean": 0.18, "n_updates": 42}, {"reward": 1170, "eps": 0.2, "len": 285, "time": 10228.66, "timesteps": 422225, "cpu_memory": 9.29, "cpu_percent": 30.9, "learning_rate": 0.00025, "loss_mean": 0.18, "n_updates": 42}, {"reward": 320, "eps": 0.2, "len": 146, "time": 10232.39, "timesteps": 422371, "cpu_memory": 9.29, "cpu_percent": 30.9, "learning_rate": 0.00025, "loss_mean": 0.2, "n_updates": 42}, {"reward": 410, "eps": 0.2, "len": 153, "time": 10236.32, "timesteps": 422524, "cpu_memory": 9.29, "cpu_percent": 30.9, "learning_rate": 0.00025, "loss_mean": 0.18, "n_updates": 42}, {"reward": 750, "eps": 0.2, "len": 312, "time": 10244.23, "timesteps": 422836, "cpu_memory": 9.29, "cpu_percent": 30.9, "learning_rate": 0.00025, "loss_mean": 0.19, "n_updates": 42}, {"reward": 270, "eps": 0.2, "len": 133, "time": 10247.65, "timesteps": 422969, "cpu_memory": 9.29, "cpu_percent": 30.9, "learning_rate": 0.00025, "loss_mean": 0.18, "n_updates": 42}, {"reward": 500, "eps": 0.2, "len": 199, "time": 10252.76, "timesteps": 423168, "cpu_memory": 9.3, "cpu_percent": 30.9, "learning_rate": 0.00025, "loss_mean": 0.18, "n_updates": 42}, {"reward": 650, "eps": 0.2, "len": 260, "time": 10259.54, "timesteps": 423428, "cpu_memory": 9.3, "cpu_percent": 30.9, "learning_rate": 0.00025, "loss_mean": 0.2, "n_updates": 42}, {"reward": 860, "eps": 0.2, "len": 262, "time": 10266.29, "timesteps": 423690, "cpu_memory": 9.3, "cpu_percent": 30.9, "learning_rate": 0.00025, "loss_mean": 0.19, "n_updates": 42}, {"reward": 440, "eps": 0.2, "len": 211, "time": 10271.63, "timesteps": 423901, "cpu_memory": 9.3, "cpu_percent": 30.9, "learning_rate": 0.00025, "loss_mean": 0.19, "n_updates": 42}, {"reward": 530, "eps": 0.2, "len": 208, "time": 10276.9, "timesteps": 424109, "cpu_memory": 9.3, "cpu_percent": 30.9, "learning_rate": 0.00025, "loss_mean": 0.18, "n_updates": 42}, {"reward": 350, "eps": 0.2, "len": 142, "time": 10280.51, "timesteps": 424251, "cpu_memory": 9.3, "cpu_percent": 30.9, "learning_rate": 0.00025, "loss_mean": 0.21, "n_updates": 42}, {"reward": 600, "eps": 0.2, "len": 181, "time": 10285.04, "timesteps": 424432, "cpu_memory": 9.3, "cpu_percent": 30.9, "learning_rate": 0.00025, "loss_mean": 0.19, "n_updates": 42}, {"reward": 530, "eps": 0.2, "len": 160, "time": 10289.34, "timesteps": 424592, "cpu_memory": 9.3, "cpu_percent": 30.9, "learning_rate": 0.00025, "loss_mean": 0.2, "n_updates": 42}, {"reward": 1000, "eps": 0.2, "len": 261, "time": 10296.1, "timesteps": 424853, "cpu_memory": 9.31, "cpu_percent": 31.0, "learning_rate": 0.00025, "loss_mean": 0.19, "n_updates": 42}, {"reward": 300, "eps": 0.2, "len": 121, "time": 10299.24, "timesteps": 424974, "cpu_memory": 9.31, "cpu_percent": 31.0, "learning_rate": 0.00025, "loss_mean": 0.2, "n_updates": 42}, {"reward": 480, "eps": 0.2, "len": 198, "time": 10304.27, "timesteps": 425172, "cpu_memory": 9.31, "cpu_percent": 31.0, "learning_rate": 0.00025, "loss_mean": 0.18, "n_updates": 42}, {"reward": 290, "eps": 0.2, "len": 184, "time": 10309.01, "timesteps": 425356, "cpu_memory": 9.31, "cpu_percent": 31.0, "learning_rate": 0.00025, "loss_mean": 0.18, "n_updates": 42}, {"reward": 390, "eps": 0.2, "len": 145, "time": 10312.71, "timesteps": 425501, "cpu_memory": 9.31, "cpu_percent": 31.0, "learning_rate": 0.00025, "loss_mean": 0.2, "n_updates": 42}, {"reward": 520, "eps": 0.2, "len": 193, "time": 10317.75, "timesteps": 425694, "cpu_memory": 9.31, "cpu_percent": 30.9, "learning_rate": 0.00025, "loss_mean": 0.18, "n_updates": 42}, {"reward": 240, "eps": 0.2, "len": 183, "time": 10322.52, "timesteps": 425877, "cpu_memory": 9.31, "cpu_percent": 31.0, "learning_rate": 0.00025, "loss_mean": 0.19, "n_updates": 42}, {"reward": 320, "eps": 0.2, "len": 167, "time": 10326.79, "timesteps": 426044, "cpu_memory": 9.31, "cpu_percent": 31.0, "learning_rate": 0.00025, "loss_mean": 0.18, "n_updates": 42}, {"reward": 380, "eps": 0.2, "len": 119, "time": 10329.84, "timesteps": 426163, "cpu_memory": 9.32, "cpu_percent": 31.0, "learning_rate": 0.00025, "loss_mean": 0.19, "n_updates": 42}, {"reward": 430, "eps": 0.2, "len": 154, "time": 10333.68, "timesteps": 426317, "cpu_memory": 9.32, "cpu_percent": 31.0, "learning_rate": 0.00025, "loss_mean": 0.2, "n_updates": 42}, {"reward": 350, "eps": 0.2, "len": 170, "time": 10338.09, "timesteps": 426487, "cpu_memory": 9.32, "cpu_percent": 31.0, "learning_rate": 0.00025, "loss_mean": 0.17, "n_updates": 42}, {"reward": 640, "eps": 0.2, "len": 241, "time": 10344.15, "timesteps": 426728, "cpu_memory": 9.32, "cpu_percent": 31.0, "learning_rate": 0.00025, "loss_mean": 0.19, "n_updates": 42}, {"reward": 270, "eps": 0.2, "len": 156, "time": 10348.29, "timesteps": 426884, "cpu_memory": 9.32, "cpu_percent": 31.0, "learning_rate": 0.00025, "loss_mean": 0.18, "n_updates": 42}, {"reward": 570, "eps": 0.2, "len": 199, "time": 10353.25, "timesteps": 427083, "cpu_memory": 9.32, "cpu_percent": 31.0, "learning_rate": 0.00025, "loss_mean": 0.18, "n_updates": 42}, {"reward": 800, "eps": 0.2, "len": 305, "time": 10361.07, "timesteps": 427388, "cpu_memory": 9.32, "cpu_percent": 31.0, "learning_rate": 0.00025, "loss_mean": 0.18, "n_updates": 42}, {"reward": 420, "eps": 0.2, "len": 129, "time": 10364.4, "timesteps": 427517, "cpu_memory": 9.32, "cpu_percent": 31.0, "learning_rate": 0.00025, "loss_mean": 0.19, "n_updates": 42}, {"reward": 330, "eps": 0.2, "len": 127, "time": 10367.63, "timesteps": 427644, "cpu_memory": 9.33, "cpu_percent": 31.0, "learning_rate": 0.00025, "loss_mean": 0.19, "n_updates": 42}, {"reward": 580, "eps": 0.2, "len": 187, "time": 10372.48, "timesteps": 427831, "cpu_memory": 9.33, "cpu_percent": 31.0, "learning_rate": 0.00025, "loss_mean": 0.19, "n_updates": 42}, {"reward": 890, "eps": 0.2, "len": 185, "time": 10377.22, "timesteps": 428016, "cpu_memory": 9.33, "cpu_percent": 31.0, "learning_rate": 0.00025, "loss_mean": 0.18, "n_updates": 42}, {"reward": 860, "eps": 0.2, "len": 309, "time": 10385.12, "timesteps": 428325, "cpu_memory": 9.33, "cpu_percent": 31.0, "learning_rate": 0.00025, "loss_mean": 0.18, "n_updates": 42}, {"reward": 560, "eps": 0.2, "len": 216, "time": 10390.57, "timesteps": 428541, "cpu_memory": 9.33, "cpu_percent": 31.1, "learning_rate": 0.00025, "loss_mean": 0.2, "n_updates": 42}, {"reward": 540, "eps": 0.2, "len": 183, "time": 10395.27, "timesteps": 428724, "cpu_memory": 9.33, "cpu_percent": 31.1, "learning_rate": 0.00025, "loss_mean": 0.18, "n_updates": 42}, {"reward": 670, "eps": 0.2, "len": 182, "time": 10399.92, "timesteps": 428906, "cpu_memory": 9.33, "cpu_percent": 31.1, "learning_rate": 0.00025, "loss_mean": 0.2, "n_updates": 42}, {"reward": 680, "eps": 0.2, "len": 207, "time": 10405.17, "timesteps": 429113, "cpu_memory": 9.34, "cpu_percent": 31.1, "learning_rate": 0.00025, "loss_mean": 0.18, "n_updates": 42}, {"reward": 540, "eps": 0.2, "len": 234, "time": 10411.24, "timesteps": 429347, "cpu_memory": 9.34, "cpu_percent": 31.1, "learning_rate": 0.00025, "loss_mean": 0.2, "n_updates": 42}, {"reward": 640, "eps": 0.2, "len": 154, "time": 10415.18, "timesteps": 429501, "cpu_memory": 9.34, "cpu_percent": 31.1, "learning_rate": 0.00025, "loss_mean": 0.18, "n_updates": 42}, {"reward": 770, "eps": 0.2, "len": 219, "time": 10420.86, "timesteps": 429720, "cpu_memory": 9.34, "cpu_percent": 31.1, "learning_rate": 0.00025, "loss_mean": 0.18, "n_updates": 42}, {"reward": 550, "eps": 0.2, "len": 189, "time": 10425.7, "timesteps": 429909, "cpu_memory": 9.34, "cpu_percent": 31.1, "learning_rate": 0.00025, "loss_mean": 0.18, "n_updates": 42}, {"reward": 190, "eps": 0.2, "len": 110, "time": 10428.78, "timesteps": 430019, "cpu_memory": 9.34, "cpu_percent": 31.1, "learning_rate": 0.00025, "loss_mean": 0.19, "n_updates": 43}, {"reward": 570, "eps": 0.2, "len": 213, "time": 10434.35, "timesteps": 430232, "cpu_memory": 9.34, "cpu_percent": 31.1, "learning_rate": 0.00025, "loss_mean": 0.19, "n_updates": 43}, {"reward": 570, "eps": 0.2, "len": 251, "time": 10440.89, "timesteps": 430483, "cpu_memory": 9.35, "cpu_percent": 31.1, "learning_rate": 0.00025, "loss_mean": 0.18, "n_updates": 43}, {"reward": 240, "eps": 0.2, "len": 88, "time": 10443.12, "timesteps": 430571, "cpu_memory": 9.35, "cpu_percent": 31.1, "learning_rate": 0.00025, "loss_mean": 0.19, "n_updates": 43}, {"reward": 500, "eps": 0.2, "len": 165, "time": 10447.34, "timesteps": 430736, "cpu_memory": 9.35, "cpu_percent": 31.1, "learning_rate": 0.00025, "loss_mean": 0.19, "n_updates": 43}, {"reward": 600, "eps": 0.2, "len": 140, "time": 10450.97, "timesteps": 430876, "cpu_memory": 9.35, "cpu_percent": 31.1, "learning_rate": 0.00025, "loss_mean": 0.2, "n_updates": 43}, {"reward": 520, "eps": 0.2, "len": 302, "time": 10458.58, "timesteps": 431178, "cpu_memory": 9.35, "cpu_percent": 31.1, "learning_rate": 0.00025, "loss_mean": 0.19, "n_updates": 43}, {"reward": 940, "eps": 0.2, "len": 261, "time": 10465.17, "timesteps": 431439, "cpu_memory": 9.35, "cpu_percent": 31.1, "learning_rate": 0.00025, "loss_mean": 0.18, "n_updates": 43}, {"reward": 970, "eps": 0.2, "len": 270, "time": 10472.09, "timesteps": 431709, "cpu_memory": 9.35, "cpu_percent": 31.1, "learning_rate": 0.00025, "loss_mean": 0.2, "n_updates": 43}, {"reward": 670, "eps": 0.2, "len": 200, "time": 10477.2, "timesteps": 431909, "cpu_memory": 9.36, "cpu_percent": 31.1, "learning_rate": 0.00025, "loss_mean": 0.19, "n_updates": 43}, {"reward": 380, "eps": 0.2, "len": 107, "time": 10480.05, "timesteps": 432016, "cpu_memory": 9.36, "cpu_percent": 31.1, "learning_rate": 0.00025, "loss_mean": 0.2, "n_updates": 43}, {"reward": 700, "eps": 0.2, "len": 197, "time": 10485.06, "timesteps": 432213, "cpu_memory": 9.36, "cpu_percent": 31.1, "learning_rate": 0.00025, "loss_mean": 0.18, "n_updates": 43}, {"reward": 530, "eps": 0.2, "len": 171, "time": 10489.51, "timesteps": 432384, "cpu_memory": 9.36, "cpu_percent": 31.1, "learning_rate": 0.00025, "loss_mean": 0.19, "n_updates": 43}, {"reward": 1280, "eps": 0.2, "len": 288, "time": 10496.8, "timesteps": 432672, "cpu_memory": 9.36, "cpu_percent": 31.1, "learning_rate": 0.00025, "loss_mean": 0.18, "n_updates": 43}, {"reward": 640, "eps": 0.2, "len": 184, "time": 10501.49, "timesteps": 432856, "cpu_memory": 9.36, "cpu_percent": 31.1, "learning_rate": 0.00025, "loss_mean": 0.18, "n_updates": 43}, {"reward": 550, "eps": 0.2, "len": 226, "time": 10507.27, "timesteps": 433082, "cpu_memory": 9.36, "cpu_percent": 31.1, "learning_rate": 0.00025, "loss_mean": 0.18, "n_updates": 43}, {"reward": 760, "eps": 0.2, "len": 213, "time": 10512.83, "timesteps": 433295, "cpu_memory": 9.36, "cpu_percent": 31.1, "learning_rate": 0.00025, "loss_mean": 0.2, "n_updates": 43}, {"reward": 540, "eps": 0.2, "len": 153, "time": 10516.72, "timesteps": 433448, "cpu_memory": 9.37, "cpu_percent": 31.1, "learning_rate": 0.00025, "loss_mean": 0.18, "n_updates": 43}, {"reward": 670, "eps": 0.2, "len": 187, "time": 10521.46, "timesteps": 433635, "cpu_memory": 9.37, "cpu_percent": 31.1, "learning_rate": 0.00025, "loss_mean": 0.2, "n_updates": 43}, {"reward": 460, "eps": 0.2, "len": 158, "time": 10525.48, "timesteps": 433793, "cpu_memory": 9.37, "cpu_percent": 31.1, "learning_rate": 0.00025, "loss_mean": 0.2, "n_updates": 43}, {"reward": 1020, "eps": 0.2, "len": 384, "time": 10535.29, "timesteps": 434177, "cpu_memory": 9.37, "cpu_percent": 31.1, "learning_rate": 0.00025, "loss_mean": 0.2, "n_updates": 43}, {"reward": 160, "eps": 0.2, "len": 87, "time": 10537.56, "timesteps": 434264, "cpu_memory": 9.37, "cpu_percent": 31.1, "learning_rate": 0.00025, "loss_mean": 0.2, "n_updates": 43}, {"reward": 690, "eps": 0.2, "len": 148, "time": 10541.34, "timesteps": 434412, "cpu_memory": 9.37, "cpu_percent": 31.2, "learning_rate": 0.00025, "loss_mean": 0.19, "n_updates": 43}, {"reward": 680, "eps": 0.2, "len": 214, "time": 10546.9, "timesteps": 434626, "cpu_memory": 9.37, "cpu_percent": 31.2, "learning_rate": 0.00025, "loss_mean": 0.19, "n_updates": 43}, {"reward": 810, "eps": 0.2, "len": 249, "time": 10553.15, "timesteps": 434875, "cpu_memory": 9.38, "cpu_percent": 31.2, "learning_rate": 0.00025, "loss_mean": 0.19, "n_updates": 43}, {"reward": 610, "eps": 0.2, "len": 182, "time": 10557.79, "timesteps": 435057, "cpu_memory": 9.38, "cpu_percent": 31.2, "learning_rate": 0.00025, "loss_mean": 0.2, "n_updates": 43}, {"reward": 290, "eps": 0.2, "len": 109, "time": 10560.56, "timesteps": 435166, "cpu_memory": 9.38, "cpu_percent": 31.2, "learning_rate": 0.00025, "loss_mean": 0.2, "n_updates": 43}, {"reward": 640, "eps": 0.2, "len": 180, "time": 10565.28, "timesteps": 435346, "cpu_memory": 9.38, "cpu_percent": 31.2, "learning_rate": 0.00025, "loss_mean": 0.2, "n_updates": 43}, {"reward": 380, "eps": 0.2, "len": 150, "time": 10569.2, "timesteps": 435496, "cpu_memory": 9.38, "cpu_percent": 31.2, "learning_rate": 0.00025, "loss_mean": 0.18, "n_updates": 43}, {"reward": 500, "eps": 0.2, "len": 201, "time": 10574.5, "timesteps": 435697, "cpu_memory": 9.38, "cpu_percent": 31.2, "learning_rate": 0.00025, "loss_mean": 0.19, "n_updates": 43}, {"reward": 880, "eps": 0.2, "len": 211, "time": 10579.93, "timesteps": 435908, "cpu_memory": 9.38, "cpu_percent": 31.2, "learning_rate": 0.00025, "loss_mean": 0.19, "n_updates": 43}, {"reward": 660, "eps": 0.2, "len": 183, "time": 10584.58, "timesteps": 436091, "cpu_memory": 9.38, "cpu_percent": 31.2, "learning_rate": 0.00025, "loss_mean": 0.2, "n_updates": 43}, {"reward": 720, "eps": 0.2, "len": 221, "time": 10590.17, "timesteps": 436312, "cpu_memory": 9.39, "cpu_percent": 31.2, "learning_rate": 0.00025, "loss_mean": 0.18, "n_updates": 43}, {"reward": 550, "eps": 0.2, "len": 179, "time": 10594.83, "timesteps": 436491, "cpu_memory": 9.39, "cpu_percent": 31.2, "learning_rate": 0.00025, "loss_mean": 0.19, "n_updates": 43}, {"reward": 870, "eps": 0.2, "len": 163, "time": 10598.99, "timesteps": 436654, "cpu_memory": 9.39, "cpu_percent": 31.3, "learning_rate": 0.00025, "loss_mean": 0.21, "n_updates": 43}, {"reward": 600, "eps": 0.2, "len": 209, "time": 10604.36, "timesteps": 436863, "cpu_memory": 9.39, "cpu_percent": 31.3, "learning_rate": 0.00025, "loss_mean": 0.18, "n_updates": 43}, {"reward": 450, "eps": 0.2, "len": 224, "time": 10610.1, "timesteps": 437087, "cpu_memory": 9.39, "cpu_percent": 31.3, "learning_rate": 0.00025, "loss_mean": 0.2, "n_updates": 43}, {"reward": 680, "eps": 0.2, "len": 193, "time": 10614.95, "timesteps": 437280, "cpu_memory": 9.39, "cpu_percent": 31.3, "learning_rate": 0.00025, "loss_mean": 0.2, "n_updates": 43}, {"reward": 670, "eps": 0.2, "len": 177, "time": 10619.44, "timesteps": 437457, "cpu_memory": 9.39, "cpu_percent": 31.3, "learning_rate": 0.00025, "loss_mean": 0.2, "n_updates": 43}, {"reward": 530, "eps": 0.2, "len": 204, "time": 10624.71, "timesteps": 437661, "cpu_memory": 9.39, "cpu_percent": 31.3, "learning_rate": 0.00025, "loss_mean": 0.19, "n_updates": 43}, {"reward": 630, "eps": 0.2, "len": 168, "time": 10628.98, "timesteps": 437829, "cpu_memory": 9.4, "cpu_percent": 31.3, "learning_rate": 0.00025, "loss_mean": 0.18, "n_updates": 43}, {"reward": 610, "eps": 0.2, "len": 216, "time": 10634.46, "timesteps": 438045, "cpu_memory": 9.4, "cpu_percent": 31.3, "learning_rate": 0.00025, "loss_mean": 0.21, "n_updates": 43}, {"reward": 480, "eps": 0.2, "len": 179, "time": 10639.19, "timesteps": 438224, "cpu_memory": 9.4, "cpu_percent": 31.3, "learning_rate": 0.00025, "loss_mean": 0.2, "n_updates": 43}, {"reward": 620, "eps": 0.2, "len": 166, "time": 10643.4, "timesteps": 438390, "cpu_memory": 9.4, "cpu_percent": 31.3, "learning_rate": 0.00025, "loss_mean": 0.19, "n_updates": 43}, {"reward": 780, "eps": 0.2, "len": 222, "time": 10648.92, "timesteps": 438612, "cpu_memory": 9.4, "cpu_percent": 31.3, "learning_rate": 0.00025, "loss_mean": 0.19, "n_updates": 43}, {"reward": 380, "eps": 0.2, "len": 145, "time": 10652.66, "timesteps": 438757, "cpu_memory": 9.4, "cpu_percent": 31.3, "learning_rate": 0.00025, "loss_mean": 0.2, "n_updates": 43}, {"reward": 380, "eps": 0.2, "len": 154, "time": 10656.78, "timesteps": 438911, "cpu_memory": 9.4, "cpu_percent": 31.3, "learning_rate": 0.00025, "loss_mean": 0.18, "n_updates": 43}, {"reward": 800, "eps": 0.2, "len": 200, "time": 10661.78, "timesteps": 439111, "cpu_memory": 9.4, "cpu_percent": 31.3, "learning_rate": 0.00025, "loss_mean": 0.2, "n_updates": 43}, {"reward": 430, "eps": 0.2, "len": 129, "time": 10665.1, "timesteps": 439240, "cpu_memory": 9.41, "cpu_percent": 31.3, "learning_rate": 0.00025, "loss_mean": 0.21, "n_updates": 43}, {"reward": 650, "eps": 0.2, "len": 295, "time": 10672.72, "timesteps": 439535, "cpu_memory": 9.41, "cpu_percent": 31.3, "learning_rate": 0.00025, "loss_mean": 0.19, "n_updates": 43}, {"reward": 810, "eps": 0.2, "len": 239, "time": 10678.79, "timesteps": 439774, "cpu_memory": 9.41, "cpu_percent": 31.3, "learning_rate": 0.00025, "loss_mean": 0.18, "n_updates": 43}, {"reward": 510, "eps": 0.2, "len": 158, "time": 10682.85, "timesteps": 439932, "cpu_memory": 9.41, "cpu_percent": 31.3, "learning_rate": 0.00025, "loss_mean": 0.2, "n_updates": 43}, {"reward": 460, "eps": 0.2, "len": 161, "time": 10687.35, "timesteps": 440093, "cpu_memory": 9.41, "cpu_percent": 31.3, "learning_rate": 0.00025, "loss_mean": 0.21, "n_updates": 44}, {"reward": 450, "eps": 0.2, "len": 147, "time": 10691.07, "timesteps": 440240, "cpu_memory": 9.41, "cpu_percent": 31.3, "learning_rate": 0.00025, "loss_mean": 0.19, "n_updates": 44}, {"reward": 580, "eps": 0.2, "len": 191, "time": 10695.92, "timesteps": 440431, "cpu_memory": 9.41, "cpu_percent": 31.3, "learning_rate": 0.00025, "loss_mean": 0.2, "n_updates": 44}, {"reward": 410, "eps": 0.2, "len": 131, "time": 10699.44, "timesteps": 440562, "cpu_memory": 9.41, "cpu_percent": 31.3, "learning_rate": 0.00025, "loss_mean": 0.19, "n_updates": 44}, {"reward": 800, "eps": 0.2, "len": 248, "time": 10705.71, "timesteps": 440810, "cpu_memory": 9.42, "cpu_percent": 31.3, "learning_rate": 0.00025, "loss_mean": 0.21, "n_updates": 44}, {"reward": 320, "eps": 0.2, "len": 166, "time": 10709.91, "timesteps": 440976, "cpu_memory": 9.42, "cpu_percent": 31.3, "learning_rate": 0.00025, "loss_mean": 0.19, "n_updates": 44}, {"reward": 590, "eps": 0.2, "len": 147, "time": 10713.68, "timesteps": 441123, "cpu_memory": 9.42, "cpu_percent": 31.3, "learning_rate": 0.00025, "loss_mean": 0.19, "n_updates": 44}, {"reward": 730, "eps": 0.2, "len": 187, "time": 10718.59, "timesteps": 441310, "cpu_memory": 9.42, "cpu_percent": 31.3, "learning_rate": 0.00025, "loss_mean": 0.2, "n_updates": 44}, {"reward": 720, "eps": 0.2, "len": 234, "time": 10724.6, "timesteps": 441544, "cpu_memory": 9.42, "cpu_percent": 31.3, "learning_rate": 0.00025, "loss_mean": 0.2, "n_updates": 44}, {"reward": 730, "eps": 0.2, "len": 178, "time": 10729.2, "timesteps": 441722, "cpu_memory": 9.42, "cpu_percent": 31.3, "learning_rate": 0.00025, "loss_mean": 0.2, "n_updates": 44}, {"reward": 330, "eps": 0.2, "len": 185, "time": 10734.05, "timesteps": 441907, "cpu_memory": 9.42, "cpu_percent": 31.4, "learning_rate": 0.00025, "loss_mean": 0.19, "n_updates": 44}, {"reward": 320, "eps": 0.2, "len": 139, "time": 10737.74, "timesteps": 442046, "cpu_memory": 9.43, "cpu_percent": 31.3, "learning_rate": 0.00025, "loss_mean": 0.2, "n_updates": 44}, {"reward": 840, "eps": 0.2, "len": 231, "time": 10743.54, "timesteps": 442277, "cpu_memory": 9.43, "cpu_percent": 31.3, "learning_rate": 0.00025, "loss_mean": 0.19, "n_updates": 44}, {"reward": 770, "eps": 0.2, "len": 222, "time": 10749.16, "timesteps": 442499, "cpu_memory": 9.43, "cpu_percent": 31.3, "learning_rate": 0.00025, "loss_mean": 0.19, "n_updates": 44}, {"reward": 660, "eps": 0.2, "len": 276, "time": 10756.18, "timesteps": 442775, "cpu_memory": 9.43, "cpu_percent": 31.3, "learning_rate": 0.00025, "loss_mean": 0.2, "n_updates": 44}, {"reward": 460, "eps": 0.2, "len": 120, "time": 10759.26, "timesteps": 442895, "cpu_memory": 9.43, "cpu_percent": 31.3, "learning_rate": 0.00025, "loss_mean": 0.2, "n_updates": 44}, {"reward": 490, "eps": 0.2, "len": 179, "time": 10763.94, "timesteps": 443074, "cpu_memory": 9.43, "cpu_percent": 31.4, "learning_rate": 0.00025, "loss_mean": 0.22, "n_updates": 44}, {"reward": 320, "eps": 0.2, "len": 145, "time": 10767.7, "timesteps": 443219, "cpu_memory": 9.43, "cpu_percent": 31.4, "learning_rate": 0.00025, "loss_mean": 0.22, "n_updates": 44}, {"reward": 460, "eps": 0.2, "len": 159, "time": 10771.76, "timesteps": 443378, "cpu_memory": 9.43, "cpu_percent": 31.4, "learning_rate": 0.00025, "loss_mean": 0.19, "n_updates": 44}, {"reward": 470, "eps": 0.2, "len": 144, "time": 10775.44, "timesteps": 443522, "cpu_memory": 9.44, "cpu_percent": 31.4, "learning_rate": 0.00025, "loss_mean": 0.2, "n_updates": 44}, {"reward": 480, "eps": 0.2, "len": 137, "time": 10779.2, "timesteps": 443659, "cpu_memory": 9.44, "cpu_percent": 31.4, "learning_rate": 0.00025, "loss_mean": 0.22, "n_updates": 44}, {"reward": 490, "eps": 0.2, "len": 174, "time": 10783.68, "timesteps": 443833, "cpu_memory": 9.44, "cpu_percent": 31.4, "learning_rate": 0.00025, "loss_mean": 0.2, "n_updates": 44}, {"reward": 510, "eps": 0.2, "len": 179, "time": 10788.26, "timesteps": 444012, "cpu_memory": 9.44, "cpu_percent": 31.4, "learning_rate": 0.00025, "loss_mean": 0.19, "n_updates": 44}, {"reward": 550, "eps": 0.2, "len": 178, "time": 10792.97, "timesteps": 444190, "cpu_memory": 9.44, "cpu_percent": 31.4, "learning_rate": 0.00025, "loss_mean": 0.22, "n_updates": 44}, {"reward": 740, "eps": 0.2, "len": 243, "time": 10799.18, "timesteps": 444433, "cpu_memory": 9.44, "cpu_percent": 31.4, "learning_rate": 0.00025, "loss_mean": 0.2, "n_updates": 44}, {"reward": 610, "eps": 0.2, "len": 198, "time": 10804.18, "timesteps": 444631, "cpu_memory": 9.44, "cpu_percent": 31.4, "learning_rate": 0.00025, "loss_mean": 0.2, "n_updates": 44}, {"reward": 650, "eps": 0.2, "len": 182, "time": 10808.89, "timesteps": 444813, "cpu_memory": 9.44, "cpu_percent": 31.4, "learning_rate": 0.00025, "loss_mean": 0.2, "n_updates": 44}, {"reward": 300, "eps": 0.2, "len": 153, "time": 10812.78, "timesteps": 444966, "cpu_memory": 9.45, "cpu_percent": 31.4, "learning_rate": 0.00025, "loss_mean": 0.19, "n_updates": 44}, {"reward": 550, "eps": 0.2, "len": 165, "time": 10816.98, "timesteps": 445131, "cpu_memory": 9.45, "cpu_percent": 31.4, "learning_rate": 0.00025, "loss_mean": 0.2, "n_updates": 44}, {"reward": 720, "eps": 0.2, "len": 246, "time": 10823.28, "timesteps": 445377, "cpu_memory": 9.45, "cpu_percent": 31.5, "learning_rate": 0.00025, "loss_mean": 0.2, "n_updates": 44}, {"reward": 720, "eps": 0.2, "len": 179, "time": 10827.91, "timesteps": 445556, "cpu_memory": 9.45, "cpu_percent": 31.5, "learning_rate": 0.00025, "loss_mean": 0.2, "n_updates": 44}, {"reward": 530, "eps": 0.2, "len": 166, "time": 10832.1, "timesteps": 445722, "cpu_memory": 9.45, "cpu_percent": 31.5, "learning_rate": 0.00025, "loss_mean": 0.2, "n_updates": 44}, {"reward": 650, "eps": 0.2, "len": 154, "time": 10836.01, "timesteps": 445876, "cpu_memory": 9.45, "cpu_percent": 31.5, "learning_rate": 0.00025, "loss_mean": 0.2, "n_updates": 44}, {"reward": 980, "eps": 0.2, "len": 264, "time": 10842.85, "timesteps": 446140, "cpu_memory": 9.45, "cpu_percent": 31.5, "learning_rate": 0.00025, "loss_mean": 0.2, "n_updates": 44}, {"reward": 400, "eps": 0.2, "len": 209, "time": 10848.26, "timesteps": 446349, "cpu_memory": 9.45, "cpu_percent": 31.5, "learning_rate": 0.00025, "loss_mean": 0.2, "n_updates": 44}, {"reward": 470, "eps": 0.2, "len": 173, "time": 10852.66, "timesteps": 446522, "cpu_memory": 9.46, "cpu_percent": 31.5, "learning_rate": 0.00025, "loss_mean": 0.18, "n_updates": 44}, {"reward": 450, "eps": 0.2, "len": 128, "time": 10856.0, "timesteps": 446650, "cpu_memory": 9.46, "cpu_percent": 31.5, "learning_rate": 0.00025, "loss_mean": 0.19, "n_updates": 44}, {"reward": 230, "eps": 0.2, "len": 163, "time": 10860.21, "timesteps": 446813, "cpu_memory": 9.46, "cpu_percent": 31.5, "learning_rate": 0.00025, "loss_mean": 0.2, "n_updates": 44}, {"reward": 670, "eps": 0.2, "len": 233, "time": 10866.05, "timesteps": 447046, "cpu_memory": 9.46, "cpu_percent": 31.5, "learning_rate": 0.00025, "loss_mean": 0.19, "n_updates": 44}, {"reward": 400, "eps": 0.2, "len": 208, "time": 10871.52, "timesteps": 447254, "cpu_memory": 9.46, "cpu_percent": 31.5, "learning_rate": 0.00025, "loss_mean": 0.2, "n_updates": 44}, {"reward": 660, "eps": 0.2, "len": 198, "time": 10876.49, "timesteps": 447452, "cpu_memory": 9.46, "cpu_percent": 31.5, "learning_rate": 0.00025, "loss_mean": 0.19, "n_updates": 44}, {"reward": 450, "eps": 0.2, "len": 174, "time": 10880.95, "timesteps": 447626, "cpu_memory": 9.46, "cpu_percent": 31.5, "learning_rate": 0.00025, "loss_mean": 0.2, "n_updates": 44}, {"reward": 580, "eps": 0.2, "len": 188, "time": 10885.77, "timesteps": 447814, "cpu_memory": 9.46, "cpu_percent": 31.5, "learning_rate": 0.00025, "loss_mean": 0.2, "n_updates": 44}, {"reward": 600, "eps": 0.2, "len": 155, "time": 10889.84, "timesteps": 447969, "cpu_memory": 9.47, "cpu_percent": 31.5, "learning_rate": 0.00025, "loss_mean": 0.2, "n_updates": 44}, {"reward": 460, "eps": 0.2, "len": 188, "time": 10894.6, "timesteps": 448157, "cpu_memory": 9.47, "cpu_percent": 31.5, "learning_rate": 0.00025, "loss_mean": 0.2, "n_updates": 44}, {"reward": 840, "eps": 0.2, "len": 223, "time": 10900.27, "timesteps": 448380, "cpu_memory": 9.47, "cpu_percent": 31.5, "learning_rate": 0.00025, "loss_mean": 0.19, "n_updates": 44}, {"reward": 340, "eps": 0.2, "len": 167, "time": 10904.55, "timesteps": 448547, "cpu_memory": 9.47, "cpu_percent": 31.5, "learning_rate": 0.00025, "loss_mean": 0.19, "n_updates": 44}, {"reward": 300, "eps": 0.2, "len": 183, "time": 10909.22, "timesteps": 448730, "cpu_memory": 9.47, "cpu_percent": 31.5, "learning_rate": 0.00025, "loss_mean": 0.19, "n_updates": 44}, {"reward": 780, "eps": 0.2, "len": 218, "time": 10914.72, "timesteps": 448948, "cpu_memory": 9.47, "cpu_percent": 31.5, "learning_rate": 0.00025, "loss_mean": 0.2, "n_updates": 44}, {"reward": 580, "eps": 0.2, "len": 243, "time": 10920.95, "timesteps": 449191, "cpu_memory": 9.47, "cpu_percent": 31.5, "learning_rate": 0.00025, "loss_mean": 0.19, "n_updates": 44}, {"reward": 470, "eps": 0.2, "len": 219, "time": 10926.48, "timesteps": 449410, "cpu_memory": 9.48, "cpu_percent": 31.5, "learning_rate": 0.00025, "loss_mean": 0.21, "n_updates": 44}, {"reward": 760, "eps": 0.2, "len": 220, "time": 10932.26, "timesteps": 449630, "cpu_memory": 9.48, "cpu_percent": 31.5, "learning_rate": 0.00025, "loss_mean": 0.21, "n_updates": 44}, {"reward": 510, "eps": 0.2, "len": 158, "time": 10936.47, "timesteps": 449788, "cpu_memory": 9.48, "cpu_percent": 31.5, "learning_rate": 0.00025, "loss_mean": 0.19, "n_updates": 44}, {"reward": 670, "eps": 0.2, "len": 252, "time": 10943.16, "timesteps": 450040, "cpu_memory": 9.48, "cpu_percent": 31.5, "learning_rate": 0.00025, "loss_mean": 0.2, "n_updates": 45}, {"reward": 480, "eps": 0.2, "len": 140, "time": 10946.75, "timesteps": 450180, "cpu_memory": 9.48, "cpu_percent": 31.5, "learning_rate": 0.00025, "loss_mean": 0.2, "n_updates": 45}, {"reward": 690, "eps": 0.2, "len": 249, "time": 10953.08, "timesteps": 450429, "cpu_memory": 9.48, "cpu_percent": 31.5, "learning_rate": 0.00025, "loss_mean": 0.19, "n_updates": 45}, {"reward": 570, "eps": 0.2, "len": 193, "time": 10957.96, "timesteps": 450622, "cpu_memory": 9.48, "cpu_percent": 31.6, "learning_rate": 0.00025, "loss_mean": 0.21, "n_updates": 45}, {"reward": 500, "eps": 0.2, "len": 125, "time": 10961.16, "timesteps": 450747, "cpu_memory": 9.49, "cpu_percent": 31.6, "learning_rate": 0.00025, "loss_mean": 0.2, "n_updates": 45}, {"reward": 600, "eps": 0.2, "len": 162, "time": 10965.46, "timesteps": 450909, "cpu_memory": 9.49, "cpu_percent": 31.6, "learning_rate": 0.00025, "loss_mean": 0.21, "n_updates": 45}, {"reward": 910, "eps": 0.2, "len": 278, "time": 10972.45, "timesteps": 451187, "cpu_memory": 9.49, "cpu_percent": 31.6, "learning_rate": 0.00025, "loss_mean": 0.2, "n_updates": 45}, {"reward": 1000, "eps": 0.2, "len": 345, "time": 10981.28, "timesteps": 451532, "cpu_memory": 9.49, "cpu_percent": 31.6, "learning_rate": 0.00025, "loss_mean": 0.2, "n_updates": 45}, {"reward": 720, "eps": 0.2, "len": 217, "time": 10986.76, "timesteps": 451749, "cpu_memory": 9.49, "cpu_percent": 31.6, "learning_rate": 0.00025, "loss_mean": 0.2, "n_updates": 45}, {"reward": 600, "eps": 0.2, "len": 225, "time": 10992.4, "timesteps": 451974, "cpu_memory": 9.49, "cpu_percent": 31.6, "learning_rate": 0.00025, "loss_mean": 0.21, "n_updates": 45}, {"reward": 460, "eps": 0.2, "len": 173, "time": 10996.86, "timesteps": 452147, "cpu_memory": 9.49, "cpu_percent": 31.6, "learning_rate": 0.00025, "loss_mean": 0.2, "n_updates": 45}, {"reward": 820, "eps": 0.2, "len": 215, "time": 11002.32, "timesteps": 452362, "cpu_memory": 9.5, "cpu_percent": 31.6, "learning_rate": 0.00025, "loss_mean": 0.22, "n_updates": 45}, {"reward": 710, "eps": 0.2, "len": 249, "time": 11008.67, "timesteps": 452611, "cpu_memory": 9.5, "cpu_percent": 31.6, "learning_rate": 0.00025, "loss_mean": 0.2, "n_updates": 45}, {"reward": 660, "eps": 0.2, "len": 215, "time": 11014.2, "timesteps": 452826, "cpu_memory": 9.5, "cpu_percent": 31.6, "learning_rate": 0.00025, "loss_mean": 0.21, "n_updates": 45}, {"reward": 560, "eps": 0.2, "len": 127, "time": 11017.42, "timesteps": 452953, "cpu_memory": 9.5, "cpu_percent": 31.6, "learning_rate": 0.00025, "loss_mean": 0.22, "n_updates": 45}, {"reward": 290, "eps": 0.2, "len": 172, "time": 11021.82, "timesteps": 453125, "cpu_memory": 9.5, "cpu_percent": 31.6, "learning_rate": 0.00025, "loss_mean": 0.2, "n_updates": 45}, {"reward": 810, "eps": 0.2, "len": 232, "time": 11027.81, "timesteps": 453357, "cpu_memory": 9.5, "cpu_percent": 31.6, "learning_rate": 0.00025, "loss_mean": 0.2, "n_updates": 45}, {"reward": 1160, "eps": 0.2, "len": 314, "time": 11035.85, "timesteps": 453671, "cpu_memory": 9.5, "cpu_percent": 31.6, "learning_rate": 0.00025, "loss_mean": 0.2, "n_updates": 45}, {"reward": 560, "eps": 0.2, "len": 171, "time": 11040.23, "timesteps": 453842, "cpu_memory": 9.51, "cpu_percent": 31.6, "learning_rate": 0.00025, "loss_mean": 0.18, "n_updates": 45}, {"reward": 580, "eps": 0.2, "len": 270, "time": 11047.23, "timesteps": 454112, "cpu_memory": 9.51, "cpu_percent": 31.6, "learning_rate": 0.00025, "loss_mean": 0.21, "n_updates": 45}, {"reward": 940, "eps": 0.2, "len": 238, "time": 11053.28, "timesteps": 454350, "cpu_memory": 9.51, "cpu_percent": 31.6, "learning_rate": 0.00025, "loss_mean": 0.21, "n_updates": 45}, {"reward": 690, "eps": 0.2, "len": 220, "time": 11059.11, "timesteps": 454570, "cpu_memory": 9.51, "cpu_percent": 31.6, "learning_rate": 0.00025, "loss_mean": 0.2, "n_updates": 45}, {"reward": 950, "eps": 0.2, "len": 222, "time": 11064.75, "timesteps": 454792, "cpu_memory": 9.51, "cpu_percent": 31.6, "learning_rate": 0.00025, "loss_mean": 0.19, "n_updates": 45}, {"reward": 280, "eps": 0.2, "len": 125, "time": 11067.94, "timesteps": 454917, "cpu_memory": 9.51, "cpu_percent": 31.6, "learning_rate": 0.00025, "loss_mean": 0.22, "n_updates": 45}, {"reward": 950, "eps": 0.2, "len": 298, "time": 11075.58, "timesteps": 455215, "cpu_memory": 9.52, "cpu_percent": 31.6, "learning_rate": 0.00025, "loss_mean": 0.19, "n_updates": 45}, {"reward": 540, "eps": 0.2, "len": 138, "time": 11079.1, "timesteps": 455353, "cpu_memory": 9.52, "cpu_percent": 31.6, "learning_rate": 0.00025, "loss_mean": 0.21, "n_updates": 45}, {"reward": 310, "eps": 0.2, "len": 127, "time": 11082.36, "timesteps": 455480, "cpu_memory": 9.52, "cpu_percent": 31.6, "learning_rate": 0.00025, "loss_mean": 0.21, "n_updates": 45}, {"reward": 380, "eps": 0.2, "len": 126, "time": 11085.69, "timesteps": 455606, "cpu_memory": 9.52, "cpu_percent": 31.6, "learning_rate": 0.00025, "loss_mean": 0.21, "n_updates": 45}, {"reward": 630, "eps": 0.2, "len": 215, "time": 11091.22, "timesteps": 455821, "cpu_memory": 9.52, "cpu_percent": 31.6, "learning_rate": 0.00025, "loss_mean": 0.2, "n_updates": 45}, {"reward": 400, "eps": 0.2, "len": 123, "time": 11094.38, "timesteps": 455944, "cpu_memory": 9.52, "cpu_percent": 31.6, "learning_rate": 0.00025, "loss_mean": 0.19, "n_updates": 45}, {"reward": 710, "eps": 0.2, "len": 191, "time": 11099.25, "timesteps": 456135, "cpu_memory": 9.52, "cpu_percent": 31.6, "learning_rate": 0.00025, "loss_mean": 0.21, "n_updates": 45}, {"reward": 440, "eps": 0.2, "len": 130, "time": 11102.57, "timesteps": 456265, "cpu_memory": 9.52, "cpu_percent": 31.6, "learning_rate": 0.00025, "loss_mean": 0.21, "n_updates": 45}, {"reward": 480, "eps": 0.2, "len": 183, "time": 11107.28, "timesteps": 456448, "cpu_memory": 9.52, "cpu_percent": 31.7, "learning_rate": 0.00025, "loss_mean": 0.2, "n_updates": 45}, {"reward": 470, "eps": 0.2, "len": 116, "time": 11110.25, "timesteps": 456564, "cpu_memory": 9.52, "cpu_percent": 31.7, "learning_rate": 0.00025, "loss_mean": 0.21, "n_updates": 45}, {"reward": 510, "eps": 0.2, "len": 251, "time": 11116.65, "timesteps": 456815, "cpu_memory": 9.53, "cpu_percent": 31.7, "learning_rate": 0.00025, "loss_mean": 0.2, "n_updates": 45}, {"reward": 450, "eps": 0.2, "len": 237, "time": 11122.54, "timesteps": 457052, "cpu_memory": 9.53, "cpu_percent": 31.7, "learning_rate": 0.00025, "loss_mean": 0.22, "n_updates": 45}, {"reward": 600, "eps": 0.2, "len": 190, "time": 11127.34, "timesteps": 457242, "cpu_memory": 9.53, "cpu_percent": 31.7, "learning_rate": 0.00025, "loss_mean": 0.21, "n_updates": 45}, {"reward": 760, "eps": 0.2, "len": 200, "time": 11132.44, "timesteps": 457442, "cpu_memory": 9.53, "cpu_percent": 31.7, "learning_rate": 0.00025, "loss_mean": 0.21, "n_updates": 45}, {"reward": 560, "eps": 0.2, "len": 197, "time": 11137.54, "timesteps": 457639, "cpu_memory": 9.53, "cpu_percent": 31.7, "learning_rate": 0.00025, "loss_mean": 0.19, "n_updates": 45}, {"reward": 440, "eps": 0.2, "len": 151, "time": 11141.4, "timesteps": 457790, "cpu_memory": 9.53, "cpu_percent": 31.7, "learning_rate": 0.00025, "loss_mean": 0.2, "n_updates": 45}, {"reward": 550, "eps": 0.2, "len": 141, "time": 11145.18, "timesteps": 457931, "cpu_memory": 9.53, "cpu_percent": 31.7, "learning_rate": 0.00025, "loss_mean": 0.19, "n_updates": 45}, {"reward": 380, "eps": 0.2, "len": 209, "time": 11150.53, "timesteps": 458140, "cpu_memory": 9.54, "cpu_percent": 31.7, "learning_rate": 0.00025, "loss_mean": 0.2, "n_updates": 45}, {"reward": 470, "eps": 0.2, "len": 170, "time": 11154.87, "timesteps": 458310, "cpu_memory": 9.54, "cpu_percent": 31.7, "learning_rate": 0.00025, "loss_mean": 0.22, "n_updates": 45}, {"reward": 770, "eps": 0.2, "len": 226, "time": 11160.63, "timesteps": 458536, "cpu_memory": 9.54, "cpu_percent": 31.7, "learning_rate": 0.00025, "loss_mean": 0.2, "n_updates": 45}, {"reward": 440, "eps": 0.2, "len": 128, "time": 11163.88, "timesteps": 458664, "cpu_memory": 9.54, "cpu_percent": 31.7, "learning_rate": 0.00025, "loss_mean": 0.2, "n_updates": 45}, {"reward": 350, "eps": 0.2, "len": 116, "time": 11166.9, "timesteps": 458780, "cpu_memory": 9.54, "cpu_percent": 31.7, "learning_rate": 0.00025, "loss_mean": 0.2, "n_updates": 45}, {"reward": 730, "eps": 0.2, "len": 223, "time": 11172.59, "timesteps": 459003, "cpu_memory": 9.54, "cpu_percent": 31.7, "learning_rate": 0.00025, "loss_mean": 0.21, "n_updates": 45}, {"reward": 720, "eps": 0.2, "len": 327, "time": 11180.92, "timesteps": 459330, "cpu_memory": 9.54, "cpu_percent": 31.7, "learning_rate": 0.00025, "loss_mean": 0.21, "n_updates": 45}, {"reward": 580, "eps": 0.2, "len": 214, "time": 11186.4, "timesteps": 459544, "cpu_memory": 9.55, "cpu_percent": 31.7, "learning_rate": 0.00025, "loss_mean": 0.19, "n_updates": 45}, {"reward": 630, "eps": 0.2, "len": 212, "time": 11191.86, "timesteps": 459756, "cpu_memory": 9.55, "cpu_percent": 31.7, "learning_rate": 0.00025, "loss_mean": 0.2, "n_updates": 45}, {"reward": 560, "eps": 0.2, "len": 194, "time": 11196.91, "timesteps": 459950, "cpu_memory": 9.55, "cpu_percent": 31.8, "learning_rate": 0.00025, "loss_mean": 0.22, "n_updates": 45}, {"reward": 380, "eps": 0.2, "len": 124, "time": 11200.52, "timesteps": 460074, "cpu_memory": 9.55, "cpu_percent": 31.8, "learning_rate": 0.00025, "loss_mean": 0.22, "n_updates": 46}, {"reward": 790, "eps": 0.2, "len": 273, "time": 11207.58, "timesteps": 460347, "cpu_memory": 9.55, "cpu_percent": 31.8, "learning_rate": 0.00025, "loss_mean": 0.21, "n_updates": 46}, {"reward": 280, "eps": 0.2, "len": 201, "time": 11212.71, "timesteps": 460548, "cpu_memory": 9.55, "cpu_percent": 31.8, "learning_rate": 0.00025, "loss_mean": 0.21, "n_updates": 46}, {"reward": 690, "eps": 0.2, "len": 222, "time": 11218.27, "timesteps": 460770, "cpu_memory": 9.55, "cpu_percent": 31.8, "learning_rate": 0.00025, "loss_mean": 0.21, "n_updates": 46}, {"reward": 560, "eps": 0.2, "len": 172, "time": 11222.67, "timesteps": 460942, "cpu_memory": 9.56, "cpu_percent": 31.8, "learning_rate": 0.00025, "loss_mean": 0.21, "n_updates": 46}, {"reward": 610, "eps": 0.2, "len": 200, "time": 11227.67, "timesteps": 461142, "cpu_memory": 9.56, "cpu_percent": 31.8, "learning_rate": 0.00025, "loss_mean": 0.2, "n_updates": 46}, {"reward": 740, "eps": 0.2, "len": 234, "time": 11233.77, "timesteps": 461376, "cpu_memory": 9.56, "cpu_percent": 31.8, "learning_rate": 0.00025, "loss_mean": 0.21, "n_updates": 46}, {"reward": 800, "eps": 0.2, "len": 279, "time": 11241.05, "timesteps": 461655, "cpu_memory": 9.56, "cpu_percent": 31.8, "learning_rate": 0.00025, "loss_mean": 0.21, "n_updates": 46}, {"reward": 410, "eps": 0.2, "len": 185, "time": 11245.76, "timesteps": 461840, "cpu_memory": 9.56, "cpu_percent": 31.8, "learning_rate": 0.00025, "loss_mean": 0.21, "n_updates": 46}, {"reward": 480, "eps": 0.2, "len": 193, "time": 11250.67, "timesteps": 462033, "cpu_memory": 9.56, "cpu_percent": 31.8, "learning_rate": 0.00025, "loss_mean": 0.2, "n_updates": 46}, {"reward": 580, "eps": 0.2, "len": 180, "time": 11255.22, "timesteps": 462213, "cpu_memory": 9.56, "cpu_percent": 31.8, "learning_rate": 0.00025, "loss_mean": 0.21, "n_updates": 46}, {"reward": 480, "eps": 0.2, "len": 144, "time": 11258.88, "timesteps": 462357, "cpu_memory": 9.56, "cpu_percent": 31.8, "learning_rate": 0.00025, "loss_mean": 0.21, "n_updates": 46}, {"reward": 620, "eps": 0.2, "len": 176, "time": 11263.49, "timesteps": 462533, "cpu_memory": 9.57, "cpu_percent": 31.8, "learning_rate": 0.00025, "loss_mean": 0.2, "n_updates": 46}, {"reward": 730, "eps": 0.2, "len": 236, "time": 11269.58, "timesteps": 462769, "cpu_memory": 9.57, "cpu_percent": 31.9, "learning_rate": 0.00025, "loss_mean": 0.21, "n_updates": 46}, {"reward": 810, "eps": 0.2, "len": 228, "time": 11275.4, "timesteps": 462997, "cpu_memory": 9.57, "cpu_percent": 31.9, "learning_rate": 0.00025, "loss_mean": 0.22, "n_updates": 46}, {"reward": 410, "eps": 0.2, "len": 151, "time": 11279.31, "timesteps": 463148, "cpu_memory": 9.57, "cpu_percent": 31.9, "learning_rate": 0.00025, "loss_mean": 0.19, "n_updates": 46}, {"reward": 510, "eps": 0.2, "len": 124, "time": 11282.48, "timesteps": 463272, "cpu_memory": 9.57, "cpu_percent": 31.9, "learning_rate": 0.00025, "loss_mean": 0.2, "n_updates": 46}, {"reward": 670, "eps": 0.2, "len": 213, "time": 11287.86, "timesteps": 463485, "cpu_memory": 9.57, "cpu_percent": 31.9, "learning_rate": 0.00025, "loss_mean": 0.21, "n_updates": 46}, {"reward": 550, "eps": 0.2, "len": 186, "time": 11292.57, "timesteps": 463671, "cpu_memory": 9.57, "cpu_percent": 31.9, "learning_rate": 0.00025, "loss_mean": 0.21, "n_updates": 46}, {"reward": 830, "eps": 0.2, "len": 273, "time": 11299.71, "timesteps": 463944, "cpu_memory": 9.58, "cpu_percent": 31.9, "learning_rate": 0.00025, "loss_mean": 0.22, "n_updates": 46}, {"reward": 160, "eps": 0.2, "len": 87, "time": 11302.04, "timesteps": 464031, "cpu_memory": 9.58, "cpu_percent": 31.9, "learning_rate": 0.00025, "loss_mean": 0.22, "n_updates": 46}, {"reward": 590, "eps": 0.2, "len": 186, "time": 11306.73, "timesteps": 464217, "cpu_memory": 9.58, "cpu_percent": 31.9, "learning_rate": 0.00025, "loss_mean": 0.2, "n_updates": 46}, {"reward": 480, "eps": 0.2, "len": 202, "time": 11311.87, "timesteps": 464419, "cpu_memory": 9.58, "cpu_percent": 31.9, "learning_rate": 0.00025, "loss_mean": 0.21, "n_updates": 46}, {"reward": 860, "eps": 0.2, "len": 265, "time": 11318.56, "timesteps": 464684, "cpu_memory": 9.58, "cpu_percent": 31.9, "learning_rate": 0.00025, "loss_mean": 0.21, "n_updates": 46}, {"reward": 440, "eps": 0.2, "len": 212, "time": 11323.95, "timesteps": 464896, "cpu_memory": 9.58, "cpu_percent": 31.9, "learning_rate": 0.00025, "loss_mean": 0.21, "n_updates": 46}, {"reward": 740, "eps": 0.2, "len": 202, "time": 11329.26, "timesteps": 465098, "cpu_memory": 9.58, "cpu_percent": 31.9, "learning_rate": 0.00025, "loss_mean": 0.2, "n_updates": 46}, {"reward": 360, "eps": 0.2, "len": 146, "time": 11333.05, "timesteps": 465244, "cpu_memory": 9.58, "cpu_percent": 31.9, "learning_rate": 0.00025, "loss_mean": 0.2, "n_updates": 46}, {"reward": 520, "eps": 0.2, "len": 202, "time": 11338.28, "timesteps": 465446, "cpu_memory": 9.59, "cpu_percent": 31.9, "learning_rate": 0.00025, "loss_mean": 0.21, "n_updates": 46}, {"reward": 500, "eps": 0.2, "len": 140, "time": 11341.9, "timesteps": 465586, "cpu_memory": 9.59, "cpu_percent": 31.9, "learning_rate": 0.00025, "loss_mean": 0.21, "n_updates": 46}, {"reward": 600, "eps": 0.2, "len": 193, "time": 11346.76, "timesteps": 465779, "cpu_memory": 9.59, "cpu_percent": 31.9, "learning_rate": 0.00025, "loss_mean": 0.19, "n_updates": 46}, {"reward": 500, "eps": 0.2, "len": 223, "time": 11352.41, "timesteps": 466002, "cpu_memory": 9.59, "cpu_percent": 31.9, "learning_rate": 0.00025, "loss_mean": 0.2, "n_updates": 46}, {"reward": 650, "eps": 0.2, "len": 225, "time": 11358.2, "timesteps": 466227, "cpu_memory": 9.59, "cpu_percent": 31.9, "learning_rate": 0.00025, "loss_mean": 0.19, "n_updates": 46}, {"reward": 420, "eps": 0.2, "len": 153, "time": 11362.22, "timesteps": 466380, "cpu_memory": 9.59, "cpu_percent": 31.9, "learning_rate": 0.00025, "loss_mean": 0.22, "n_updates": 46}, {"reward": 710, "eps": 0.2, "len": 204, "time": 11367.38, "timesteps": 466584, "cpu_memory": 9.59, "cpu_percent": 31.9, "learning_rate": 0.00025, "loss_mean": 0.21, "n_updates": 46}, {"reward": 720, "eps": 0.2, "len": 214, "time": 11372.8, "timesteps": 466798, "cpu_memory": 9.6, "cpu_percent": 31.9, "learning_rate": 0.00025, "loss_mean": 0.22, "n_updates": 46}, {"reward": 400, "eps": 0.2, "len": 159, "time": 11376.88, "timesteps": 466957, "cpu_memory": 9.6, "cpu_percent": 31.9, "learning_rate": 0.00025, "loss_mean": 0.21, "n_updates": 46}, {"reward": 600, "eps": 0.2, "len": 186, "time": 11381.67, "timesteps": 467143, "cpu_memory": 9.6, "cpu_percent": 31.9, "learning_rate": 0.00025, "loss_mean": 0.22, "n_updates": 46}, {"reward": 400, "eps": 0.2, "len": 134, "time": 11385.1, "timesteps": 467277, "cpu_memory": 9.6, "cpu_percent": 31.9, "learning_rate": 0.00025, "loss_mean": 0.21, "n_updates": 46}, {"reward": 730, "eps": 0.2, "len": 231, "time": 11391.06, "timesteps": 467508, "cpu_memory": 9.6, "cpu_percent": 31.9, "learning_rate": 0.00025, "loss_mean": 0.21, "n_updates": 46}, {"reward": 810, "eps": 0.2, "len": 197, "time": 11396.16, "timesteps": 467705, "cpu_memory": 9.6, "cpu_percent": 31.9, "learning_rate": 0.00025, "loss_mean": 0.21, "n_updates": 46}, {"reward": 490, "eps": 0.2, "len": 146, "time": 11399.98, "timesteps": 467851, "cpu_memory": 9.6, "cpu_percent": 31.9, "learning_rate": 0.00025, "loss_mean": 0.19, "n_updates": 46}, {"reward": 470, "eps": 0.2, "len": 157, "time": 11404.01, "timesteps": 468008, "cpu_memory": 9.6, "cpu_percent": 31.9, "learning_rate": 0.00025, "loss_mean": 0.2, "n_updates": 46}, {"reward": 400, "eps": 0.2, "len": 160, "time": 11408.13, "timesteps": 468168, "cpu_memory": 9.6, "cpu_percent": 31.9, "learning_rate": 0.00025, "loss_mean": 0.2, "n_updates": 46}, {"reward": 600, "eps": 0.2, "len": 149, "time": 11411.96, "timesteps": 468317, "cpu_memory": 9.61, "cpu_percent": 31.9, "learning_rate": 0.00025, "loss_mean": 0.22, "n_updates": 46}, {"reward": 520, "eps": 0.2, "len": 150, "time": 11415.77, "timesteps": 468467, "cpu_memory": 9.61, "cpu_percent": 31.9, "learning_rate": 0.00025, "loss_mean": 0.2, "n_updates": 46}, {"reward": 450, "eps": 0.2, "len": 220, "time": 11421.49, "timesteps": 468687, "cpu_memory": 9.61, "cpu_percent": 32.0, "learning_rate": 0.00025, "loss_mean": 0.21, "n_updates": 46}, {"reward": 560, "eps": 0.2, "len": 171, "time": 11426.04, "timesteps": 468858, "cpu_memory": 9.61, "cpu_percent": 32.0, "learning_rate": 0.00025, "loss_mean": 0.19, "n_updates": 46}, {"reward": 350, "eps": 0.2, "len": 153, "time": 11429.96, "timesteps": 469011, "cpu_memory": 9.61, "cpu_percent": 31.9, "learning_rate": 0.00025, "loss_mean": 0.22, "n_updates": 46}, {"reward": 420, "eps": 0.2, "len": 138, "time": 11433.47, "timesteps": 469149, "cpu_memory": 9.61, "cpu_percent": 31.9, "learning_rate": 0.00025, "loss_mean": 0.22, "n_updates": 46}, {"reward": 990, "eps": 0.2, "len": 375, "time": 11442.94, "timesteps": 469524, "cpu_memory": 9.61, "cpu_percent": 32.0, "learning_rate": 0.00025, "loss_mean": 0.21, "n_updates": 46}, {"reward": 520, "eps": 0.2, "len": 268, "time": 11449.88, "timesteps": 469792, "cpu_memory": 9.62, "cpu_percent": 32.0, "learning_rate": 0.00025, "loss_mean": 0.21, "n_updates": 46}, {"reward": 540, "eps": 0.2, "len": 242, "time": 11456.36, "timesteps": 470034, "cpu_memory": 9.62, "cpu_percent": 32.0, "learning_rate": 0.00025, "loss_mean": 0.2, "n_updates": 47}, {"reward": 370, "eps": 0.2, "len": 129, "time": 11459.64, "timesteps": 470163, "cpu_memory": 9.62, "cpu_percent": 32.0, "learning_rate": 0.00025, "loss_mean": 0.2, "n_updates": 47}, {"reward": 740, "eps": 0.2, "len": 205, "time": 11464.79, "timesteps": 470368, "cpu_memory": 9.62, "cpu_percent": 32.0, "learning_rate": 0.00025, "loss_mean": 0.21, "n_updates": 47}, {"reward": 380, "eps": 0.2, "len": 158, "time": 11468.8, "timesteps": 470526, "cpu_memory": 9.62, "cpu_percent": 32.0, "learning_rate": 0.00025, "loss_mean": 0.19, "n_updates": 47}, {"reward": 610, "eps": 0.2, "len": 157, "time": 11472.74, "timesteps": 470683, "cpu_memory": 9.62, "cpu_percent": 32.0, "learning_rate": 0.00025, "loss_mean": 0.2, "n_updates": 47}, {"reward": 400, "eps": 0.2, "len": 184, "time": 11477.41, "timesteps": 470867, "cpu_memory": 9.62, "cpu_percent": 32.0, "learning_rate": 0.00025, "loss_mean": 0.21, "n_updates": 47}, {"reward": 540, "eps": 0.2, "len": 152, "time": 11481.36, "timesteps": 471019, "cpu_memory": 9.62, "cpu_percent": 32.0, "learning_rate": 0.00025, "loss_mean": 0.2, "n_updates": 47}, {"reward": 600, "eps": 0.2, "len": 160, "time": 11485.49, "timesteps": 471179, "cpu_memory": 9.63, "cpu_percent": 32.0, "learning_rate": 0.00025, "loss_mean": 0.21, "n_updates": 47}, {"reward": 560, "eps": 0.2, "len": 202, "time": 11490.62, "timesteps": 471381, "cpu_memory": 9.63, "cpu_percent": 32.0, "learning_rate": 0.00025, "loss_mean": 0.21, "n_updates": 47}, {"reward": 470, "eps": 0.2, "len": 165, "time": 11494.79, "timesteps": 471546, "cpu_memory": 9.63, "cpu_percent": 32.0, "learning_rate": 0.00025, "loss_mean": 0.21, "n_updates": 47}, {"reward": 910, "eps": 0.2, "len": 262, "time": 11501.53, "timesteps": 471808, "cpu_memory": 9.63, "cpu_percent": 32.0, "learning_rate": 0.00025, "loss_mean": 0.21, "n_updates": 47}, {"reward": 260, "eps": 0.2, "len": 115, "time": 11504.5, "timesteps": 471923, "cpu_memory": 9.63, "cpu_percent": 32.0, "learning_rate": 0.00025, "loss_mean": 0.21, "n_updates": 47}, {"reward": 440, "eps": 0.2, "len": 128, "time": 11507.84, "timesteps": 472051, "cpu_memory": 9.63, "cpu_percent": 32.0, "learning_rate": 0.00025, "loss_mean": 0.23, "n_updates": 47}, {"reward": 760, "eps": 0.2, "len": 247, "time": 11514.22, "timesteps": 472298, "cpu_memory": 9.63, "cpu_percent": 32.0, "learning_rate": 0.00025, "loss_mean": 0.21, "n_updates": 47}, {"reward": 480, "eps": 0.2, "len": 135, "time": 11517.77, "timesteps": 472433, "cpu_memory": 9.63, "cpu_percent": 32.0, "learning_rate": 0.00025, "loss_mean": 0.22, "n_updates": 47}, {"reward": 560, "eps": 0.2, "len": 197, "time": 11522.8, "timesteps": 472630, "cpu_memory": 9.64, "cpu_percent": 32.0, "learning_rate": 0.00025, "loss_mean": 0.22, "n_updates": 47}, {"reward": 750, "eps": 0.2, "len": 190, "time": 11527.63, "timesteps": 472820, "cpu_memory": 9.64, "cpu_percent": 32.1, "learning_rate": 0.00025, "loss_mean": 0.21, "n_updates": 47}, {"reward": 690, "eps": 0.2, "len": 148, "time": 11531.42, "timesteps": 472968, "cpu_memory": 9.64, "cpu_percent": 32.1, "learning_rate": 0.00025, "loss_mean": 0.21, "n_updates": 47}, {"reward": 680, "eps": 0.2, "len": 193, "time": 11536.37, "timesteps": 473161, "cpu_memory": 9.64, "cpu_percent": 32.1, "learning_rate": 0.00025, "loss_mean": 0.21, "n_updates": 47}, {"reward": 720, "eps": 0.2, "len": 168, "time": 11540.63, "timesteps": 473329, "cpu_memory": 9.64, "cpu_percent": 32.1, "learning_rate": 0.00025, "loss_mean": 0.21, "n_updates": 47}, {"reward": 270, "eps": 0.2, "len": 131, "time": 11544.06, "timesteps": 473460, "cpu_memory": 9.64, "cpu_percent": 32.1, "learning_rate": 0.00025, "loss_mean": 0.23, "n_updates": 47}, {"reward": 530, "eps": 0.2, "len": 169, "time": 11548.39, "timesteps": 473629, "cpu_memory": 9.64, "cpu_percent": 32.1, "learning_rate": 0.00025, "loss_mean": 0.24, "n_updates": 47}, {"reward": 810, "eps": 0.2, "len": 216, "time": 11553.82, "timesteps": 473845, "cpu_memory": 9.64, "cpu_percent": 32.1, "learning_rate": 0.00025, "loss_mean": 0.22, "n_updates": 47}, {"reward": 490, "eps": 0.2, "len": 173, "time": 11558.31, "timesteps": 474018, "cpu_memory": 9.64, "cpu_percent": 32.1, "learning_rate": 0.00025, "loss_mean": 0.22, "n_updates": 47}, {"reward": 740, "eps": 0.2, "len": 190, "time": 11563.2, "timesteps": 474208, "cpu_memory": 9.65, "cpu_percent": 32.1, "learning_rate": 0.00025, "loss_mean": 0.22, "n_updates": 47}, {"reward": 260, "eps": 0.2, "len": 91, "time": 11565.57, "timesteps": 474299, "cpu_memory": 9.65, "cpu_percent": 32.1, "learning_rate": 0.00025, "loss_mean": 0.23, "n_updates": 47}, {"reward": 510, "eps": 0.2, "len": 225, "time": 11571.24, "timesteps": 474524, "cpu_memory": 9.65, "cpu_percent": 32.1, "learning_rate": 0.00025, "loss_mean": 0.2, "n_updates": 47}, {"reward": 270, "eps": 0.2, "len": 107, "time": 11574.04, "timesteps": 474631, "cpu_memory": 9.65, "cpu_percent": 32.1, "learning_rate": 0.00025, "loss_mean": 0.2, "n_updates": 47}, {"reward": 330, "eps": 0.2, "len": 103, "time": 11576.76, "timesteps": 474734, "cpu_memory": 9.65, "cpu_percent": 32.1, "learning_rate": 0.00025, "loss_mean": 0.19, "n_updates": 47}, {"reward": 810, "eps": 0.2, "len": 258, "time": 11583.29, "timesteps": 474992, "cpu_memory": 9.65, "cpu_percent": 32.1, "learning_rate": 0.00025, "loss_mean": 0.22, "n_updates": 47}, {"reward": 580, "eps": 0.2, "len": 149, "time": 11587.09, "timesteps": 475141, "cpu_memory": 9.65, "cpu_percent": 32.1, "learning_rate": 0.00025, "loss_mean": 0.21, "n_updates": 47}, {"reward": 520, "eps": 0.2, "len": 141, "time": 11590.69, "timesteps": 475282, "cpu_memory": 9.65, "cpu_percent": 32.1, "learning_rate": 0.00025, "loss_mean": 0.19, "n_updates": 47}, {"reward": 480, "eps": 0.2, "len": 146, "time": 11594.33, "timesteps": 475428, "cpu_memory": 9.65, "cpu_percent": 32.1, "learning_rate": 0.00025, "loss_mean": 0.2, "n_updates": 47}, {"reward": 590, "eps": 0.2, "len": 203, "time": 11599.42, "timesteps": 475631, "cpu_memory": 9.66, "cpu_percent": 32.1, "learning_rate": 0.00025, "loss_mean": 0.22, "n_updates": 47}, {"reward": 630, "eps": 0.2, "len": 201, "time": 11604.48, "timesteps": 475832, "cpu_memory": 9.66, "cpu_percent": 32.1, "learning_rate": 0.00025, "loss_mean": 0.22, "n_updates": 47}, {"reward": 450, "eps": 0.2, "len": 156, "time": 11608.7, "timesteps": 475988, "cpu_memory": 9.66, "cpu_percent": 32.1, "learning_rate": 0.00025, "loss_mean": 0.21, "n_updates": 47}, {"reward": 1230, "eps": 0.2, "len": 347, "time": 11617.4, "timesteps": 476335, "cpu_memory": 9.66, "cpu_percent": 32.1, "learning_rate": 0.00025, "loss_mean": 0.22, "n_updates": 47}, {"reward": 700, "eps": 0.2, "len": 196, "time": 11622.38, "timesteps": 476531, "cpu_memory": 9.66, "cpu_percent": 32.1, "learning_rate": 0.00025, "loss_mean": 0.2, "n_updates": 47}, {"reward": 530, "eps": 0.2, "len": 158, "time": 11626.33, "timesteps": 476689, "cpu_memory": 9.66, "cpu_percent": 32.1, "learning_rate": 0.00025, "loss_mean": 0.21, "n_updates": 47}, {"reward": 290, "eps": 0.2, "len": 154, "time": 11630.2, "timesteps": 476843, "cpu_memory": 9.66, "cpu_percent": 32.1, "learning_rate": 0.00025, "loss_mean": 0.22, "n_updates": 47}, {"reward": 470, "eps": 0.2, "len": 206, "time": 11635.49, "timesteps": 477049, "cpu_memory": 9.67, "cpu_percent": 32.1, "learning_rate": 0.00025, "loss_mean": 0.21, "n_updates": 47}, {"reward": 380, "eps": 0.2, "len": 115, "time": 11638.52, "timesteps": 477164, "cpu_memory": 9.67, "cpu_percent": 32.1, "learning_rate": 0.00025, "loss_mean": 0.21, "n_updates": 47}, {"reward": 750, "eps": 0.2, "len": 253, "time": 11645.12, "timesteps": 477417, "cpu_memory": 9.67, "cpu_percent": 32.1, "learning_rate": 0.00025, "loss_mean": 0.22, "n_updates": 47}, {"reward": 700, "eps": 0.2, "len": 245, "time": 11651.54, "timesteps": 477662, "cpu_memory": 9.67, "cpu_percent": 32.1, "learning_rate": 0.00025, "loss_mean": 0.21, "n_updates": 47}, {"reward": 700, "eps": 0.2, "len": 188, "time": 11656.28, "timesteps": 477850, "cpu_memory": 9.67, "cpu_percent": 32.1, "learning_rate": 0.00025, "loss_mean": 0.22, "n_updates": 47}, {"reward": 1050, "eps": 0.2, "len": 347, "time": 11665.04, "timesteps": 478197, "cpu_memory": 9.67, "cpu_percent": 32.1, "learning_rate": 0.00025, "loss_mean": 0.21, "n_updates": 47}, {"reward": 580, "eps": 0.2, "len": 232, "time": 11671.16, "timesteps": 478429, "cpu_memory": 9.67, "cpu_percent": 32.1, "learning_rate": 0.00025, "loss_mean": 0.21, "n_updates": 47}, {"reward": 830, "eps": 0.2, "len": 302, "time": 11678.85, "timesteps": 478731, "cpu_memory": 9.68, "cpu_percent": 32.2, "learning_rate": 0.00025, "loss_mean": 0.21, "n_updates": 47}, {"reward": 410, "eps": 0.2, "len": 151, "time": 11682.73, "timesteps": 478882, "cpu_memory": 9.68, "cpu_percent": 32.2, "learning_rate": 0.00025, "loss_mean": 0.22, "n_updates": 47}, {"reward": 180, "eps": 0.2, "len": 158, "time": 11686.86, "timesteps": 479040, "cpu_memory": 9.68, "cpu_percent": 32.2, "learning_rate": 0.00025, "loss_mean": 0.22, "n_updates": 47}, {"reward": 420, "eps": 0.2, "len": 145, "time": 11690.6, "timesteps": 479185, "cpu_memory": 9.68, "cpu_percent": 32.2, "learning_rate": 0.00025, "loss_mean": 0.24, "n_updates": 47}, {"reward": 560, "eps": 0.2, "len": 228, "time": 11696.39, "timesteps": 479413, "cpu_memory": 9.68, "cpu_percent": 32.2, "learning_rate": 0.00025, "loss_mean": 0.22, "n_updates": 47}, {"reward": 690, "eps": 0.2, "len": 237, "time": 11702.67, "timesteps": 479650, "cpu_memory": 9.68, "cpu_percent": 32.2, "learning_rate": 0.00025, "loss_mean": 0.21, "n_updates": 47}, {"reward": 560, "eps": 0.2, "len": 174, "time": 11707.1, "timesteps": 479824, "cpu_memory": 9.68, "cpu_percent": 32.2, "learning_rate": 0.00025, "loss_mean": 0.21, "n_updates": 47}, {"reward": 550, "eps": 0.2, "len": 199, "time": 11712.34, "timesteps": 480023, "cpu_memory": 9.69, "cpu_percent": 32.2, "learning_rate": 0.00025, "loss_mean": 0.22, "n_updates": 48}, {"reward": 390, "eps": 0.2, "len": 123, "time": 11715.5, "timesteps": 480146, "cpu_memory": 9.69, "cpu_percent": 32.2, "learning_rate": 0.00025, "loss_mean": 0.2, "n_updates": 48}, {"reward": 470, "eps": 0.2, "len": 233, "time": 11721.38, "timesteps": 480379, "cpu_memory": 9.69, "cpu_percent": 32.2, "learning_rate": 0.00025, "loss_mean": 0.21, "n_updates": 48}, {"reward": 650, "eps": 0.2, "len": 181, "time": 11726.06, "timesteps": 480560, "cpu_memory": 9.69, "cpu_percent": 32.2, "learning_rate": 0.00025, "loss_mean": 0.21, "n_updates": 48}, {"reward": 530, "eps": 0.2, "len": 126, "time": 11729.3, "timesteps": 480686, "cpu_memory": 9.69, "cpu_percent": 32.2, "learning_rate": 0.00025, "loss_mean": 0.22, "n_updates": 48}, {"reward": 680, "eps": 0.2, "len": 176, "time": 11734.01, "timesteps": 480862, "cpu_memory": 9.69, "cpu_percent": 32.2, "learning_rate": 0.00025, "loss_mean": 0.21, "n_updates": 48}, {"reward": 280, "eps": 0.2, "len": 150, "time": 11737.82, "timesteps": 481012, "cpu_memory": 9.69, "cpu_percent": 32.3, "learning_rate": 0.00025, "loss_mean": 0.22, "n_updates": 48}, {"reward": 550, "eps": 0.2, "len": 184, "time": 11742.48, "timesteps": 481196, "cpu_memory": 9.69, "cpu_percent": 32.3, "learning_rate": 0.00025, "loss_mean": 0.21, "n_updates": 48}, {"reward": 400, "eps": 0.2, "len": 132, "time": 11745.93, "timesteps": 481328, "cpu_memory": 9.7, "cpu_percent": 32.3, "learning_rate": 0.00025, "loss_mean": 0.21, "n_updates": 48}, {"reward": 230, "eps": 0.2, "len": 120, "time": 11749.03, "timesteps": 481448, "cpu_memory": 9.7, "cpu_percent": 32.3, "learning_rate": 0.00025, "loss_mean": 0.22, "n_updates": 48}, {"reward": 610, "eps": 0.2, "len": 190, "time": 11753.84, "timesteps": 481638, "cpu_memory": 9.7, "cpu_percent": 32.3, "learning_rate": 0.00025, "loss_mean": 0.2, "n_updates": 48}, {"reward": 490, "eps": 0.2, "len": 194, "time": 11758.71, "timesteps": 481832, "cpu_memory": 9.7, "cpu_percent": 32.3, "learning_rate": 0.00025, "loss_mean": 0.21, "n_updates": 48}, {"reward": 450, "eps": 0.2, "len": 158, "time": 11762.93, "timesteps": 481990, "cpu_memory": 9.7, "cpu_percent": 32.3, "learning_rate": 0.00025, "loss_mean": 0.22, "n_updates": 48}, {"reward": 600, "eps": 0.2, "len": 158, "time": 11767.02, "timesteps": 482148, "cpu_memory": 9.7, "cpu_percent": 32.3, "learning_rate": 0.00025, "loss_mean": 0.22, "n_updates": 48}, {"reward": 440, "eps": 0.2, "len": 218, "time": 11772.49, "timesteps": 482366, "cpu_memory": 9.7, "cpu_percent": 32.3, "learning_rate": 0.00025, "loss_mean": 0.21, "n_updates": 48}, {"reward": 320, "eps": 0.2, "len": 158, "time": 11776.5, "timesteps": 482524, "cpu_memory": 9.7, "cpu_percent": 32.3, "learning_rate": 0.00025, "loss_mean": 0.22, "n_updates": 48}, {"reward": 400, "eps": 0.2, "len": 146, "time": 11780.23, "timesteps": 482670, "cpu_memory": 9.7, "cpu_percent": 32.3, "learning_rate": 0.00025, "loss_mean": 0.2, "n_updates": 48}, {"reward": 490, "eps": 0.2, "len": 152, "time": 11784.04, "timesteps": 482822, "cpu_memory": 9.71, "cpu_percent": 32.3, "learning_rate": 0.00025, "loss_mean": 0.23, "n_updates": 48}, {"reward": 330, "eps": 0.2, "len": 136, "time": 11787.49, "timesteps": 482958, "cpu_memory": 9.71, "cpu_percent": 32.3, "learning_rate": 0.00025, "loss_mean": 0.23, "n_updates": 48}, {"reward": 700, "eps": 0.2, "len": 226, "time": 11793.32, "timesteps": 483184, "cpu_memory": 9.71, "cpu_percent": 32.3, "learning_rate": 0.00025, "loss_mean": 0.21, "n_updates": 48}, {"reward": 280, "eps": 0.2, "len": 120, "time": 11796.47, "timesteps": 483304, "cpu_memory": 9.71, "cpu_percent": 32.3, "learning_rate": 0.00025, "loss_mean": 0.22, "n_updates": 48}, {"reward": 220, "eps": 0.2, "len": 113, "time": 11799.4, "timesteps": 483417, "cpu_memory": 9.71, "cpu_percent": 32.3, "learning_rate": 0.00025, "loss_mean": 0.21, "n_updates": 48}, {"reward": 450, "eps": 0.2, "len": 139, "time": 11802.97, "timesteps": 483556, "cpu_memory": 9.71, "cpu_percent": 32.3, "learning_rate": 0.00025, "loss_mean": 0.21, "n_updates": 48}, {"reward": 180, "eps": 0.2, "len": 123, "time": 11806.18, "timesteps": 483679, "cpu_memory": 9.71, "cpu_percent": 32.3, "learning_rate": 0.00025, "loss_mean": 0.21, "n_updates": 48}, {"reward": 720, "eps": 0.2, "len": 169, "time": 11810.51, "timesteps": 483848, "cpu_memory": 9.71, "cpu_percent": 32.3, "learning_rate": 0.00025, "loss_mean": 0.21, "n_updates": 48}, {"reward": 720, "eps": 0.2, "len": 233, "time": 11816.56, "timesteps": 484081, "cpu_memory": 9.71, "cpu_percent": 32.3, "learning_rate": 0.00025, "loss_mean": 0.21, "n_updates": 48}, {"reward": 320, "eps": 0.2, "len": 112, "time": 11819.47, "timesteps": 484193, "cpu_memory": 9.71, "cpu_percent": 32.3, "learning_rate": 0.00025, "loss_mean": 0.23, "n_updates": 48}, {"reward": 500, "eps": 0.2, "len": 245, "time": 11825.91, "timesteps": 484438, "cpu_memory": 9.72, "cpu_percent": 32.3, "learning_rate": 0.00025, "loss_mean": 0.23, "n_updates": 48}, {"reward": 510, "eps": 0.2, "len": 154, "time": 11829.88, "timesteps": 484592, "cpu_memory": 9.72, "cpu_percent": 32.3, "learning_rate": 0.00025, "loss_mean": 0.22, "n_updates": 48}, {"reward": 580, "eps": 0.2, "len": 149, "time": 11833.61, "timesteps": 484741, "cpu_memory": 9.72, "cpu_percent": 32.3, "learning_rate": 0.00025, "loss_mean": 0.21, "n_updates": 48}, {"reward": 640, "eps": 0.2, "len": 186, "time": 11838.51, "timesteps": 484927, "cpu_memory": 9.72, "cpu_percent": 32.3, "learning_rate": 0.00025, "loss_mean": 0.21, "n_updates": 48}, {"reward": 700, "eps": 0.2, "len": 160, "time": 11842.55, "timesteps": 485087, "cpu_memory": 9.72, "cpu_percent": 32.3, "learning_rate": 0.00025, "loss_mean": 0.2, "n_updates": 48}, {"reward": 850, "eps": 0.2, "len": 213, "time": 11847.95, "timesteps": 485300, "cpu_memory": 9.72, "cpu_percent": 32.3, "learning_rate": 0.00025, "loss_mean": 0.22, "n_updates": 48}, {"reward": 530, "eps": 0.2, "len": 156, "time": 11851.98, "timesteps": 485456, "cpu_memory": 9.72, "cpu_percent": 32.3, "learning_rate": 0.00025, "loss_mean": 0.24, "n_updates": 48}, {"reward": 690, "eps": 0.2, "len": 196, "time": 11857.11, "timesteps": 485652, "cpu_memory": 9.72, "cpu_percent": 32.3, "learning_rate": 0.00025, "loss_mean": 0.22, "n_updates": 48}, {"reward": 390, "eps": 0.2, "len": 128, "time": 11860.38, "timesteps": 485780, "cpu_memory": 9.73, "cpu_percent": 32.3, "learning_rate": 0.00025, "loss_mean": 0.2, "n_updates": 48}, {"reward": 570, "eps": 0.2, "len": 163, "time": 11864.51, "timesteps": 485943, "cpu_memory": 9.73, "cpu_percent": 32.3, "learning_rate": 0.00025, "loss_mean": 0.22, "n_updates": 48}, {"reward": 610, "eps": 0.2, "len": 164, "time": 11868.76, "timesteps": 486107, "cpu_memory": 9.73, "cpu_percent": 32.4, "learning_rate": 0.00025, "loss_mean": 0.21, "n_updates": 48}, {"reward": 650, "eps": 0.2, "len": 182, "time": 11873.33, "timesteps": 486289, "cpu_memory": 9.73, "cpu_percent": 32.4, "learning_rate": 0.00025, "loss_mean": 0.23, "n_updates": 48}, {"reward": 520, "eps": 0.2, "len": 280, "time": 11880.45, "timesteps": 486569, "cpu_memory": 9.73, "cpu_percent": 32.4, "learning_rate": 0.00025, "loss_mean": 0.21, "n_updates": 48}, {"reward": 660, "eps": 0.2, "len": 168, "time": 11884.83, "timesteps": 486737, "cpu_memory": 9.73, "cpu_percent": 32.4, "learning_rate": 0.00025, "loss_mean": 0.22, "n_updates": 48}, {"reward": 410, "eps": 0.2, "len": 188, "time": 11889.77, "timesteps": 486925, "cpu_memory": 9.73, "cpu_percent": 32.4, "learning_rate": 0.00025, "loss_mean": 0.22, "n_updates": 48}, {"reward": 440, "eps": 0.2, "len": 121, "time": 11892.9, "timesteps": 487046, "cpu_memory": 9.73, "cpu_percent": 32.4, "learning_rate": 0.00025, "loss_mean": 0.2, "n_updates": 48}, {"reward": 360, "eps": 0.2, "len": 134, "time": 11896.31, "timesteps": 487180, "cpu_memory": 9.74, "cpu_percent": 32.4, "learning_rate": 0.00025, "loss_mean": 0.21, "n_updates": 48}, {"reward": 540, "eps": 0.2, "len": 200, "time": 11901.41, "timesteps": 487380, "cpu_memory": 9.74, "cpu_percent": 32.4, "learning_rate": 0.00025, "loss_mean": 0.21, "n_updates": 48}, {"reward": 390, "eps": 0.2, "len": 143, "time": 11905.14, "timesteps": 487523, "cpu_memory": 9.74, "cpu_percent": 32.4, "learning_rate": 0.00025, "loss_mean": 0.21, "n_updates": 48}, {"reward": 790, "eps": 0.2, "len": 233, "time": 11911.04, "timesteps": 487756, "cpu_memory": 9.74, "cpu_percent": 32.3, "learning_rate": 0.00025, "loss_mean": 0.21, "n_updates": 48}, {"reward": 240, "eps": 0.2, "len": 137, "time": 11914.6, "timesteps": 487893, "cpu_memory": 9.74, "cpu_percent": 32.3, "learning_rate": 0.00025, "loss_mean": 0.23, "n_updates": 48}, {"reward": 780, "eps": 0.2, "len": 185, "time": 11919.47, "timesteps": 488078, "cpu_memory": 9.74, "cpu_percent": 32.3, "learning_rate": 0.00025, "loss_mean": 0.22, "n_updates": 48}, {"reward": 360, "eps": 0.2, "len": 106, "time": 11922.29, "timesteps": 488184, "cpu_memory": 9.74, "cpu_percent": 32.4, "learning_rate": 0.00025, "loss_mean": 0.2, "n_updates": 48}, {"reward": 640, "eps": 0.2, "len": 161, "time": 11926.38, "timesteps": 488345, "cpu_memory": 9.74, "cpu_percent": 32.4, "learning_rate": 0.00025, "loss_mean": 0.21, "n_updates": 48}, {"reward": 530, "eps": 0.2, "len": 175, "time": 11930.89, "timesteps": 488520, "cpu_memory": 9.74, "cpu_percent": 32.4, "learning_rate": 0.00025, "loss_mean": 0.22, "n_updates": 48}, {"reward": 690, "eps": 0.2, "len": 235, "time": 11937.11, "timesteps": 488755, "cpu_memory": 9.75, "cpu_percent": 32.4, "learning_rate": 0.00025, "loss_mean": 0.21, "n_updates": 48}, {"reward": 330, "eps": 0.2, "len": 154, "time": 11940.98, "timesteps": 488909, "cpu_memory": 9.75, "cpu_percent": 32.4, "learning_rate": 0.00025, "loss_mean": 0.2, "n_updates": 48}, {"reward": 520, "eps": 0.2, "len": 162, "time": 11945.09, "timesteps": 489071, "cpu_memory": 9.75, "cpu_percent": 32.4, "learning_rate": 0.00025, "loss_mean": 0.22, "n_updates": 48}, {"reward": 550, "eps": 0.2, "len": 192, "time": 11950.09, "timesteps": 489263, "cpu_memory": 9.75, "cpu_percent": 32.4, "learning_rate": 0.00025, "loss_mean": 0.22, "n_updates": 48}, {"reward": 650, "eps": 0.2, "len": 213, "time": 11955.5, "timesteps": 489476, "cpu_memory": 9.75, "cpu_percent": 32.4, "learning_rate": 0.00025, "loss_mean": 0.18, "n_updates": 48}, {"reward": 810, "eps": 0.2, "len": 261, "time": 11962.1, "timesteps": 489737, "cpu_memory": 9.75, "cpu_percent": 32.4, "learning_rate": 0.00025, "loss_mean": 0.23, "n_updates": 48}, {"reward": 400, "eps": 0.2, "len": 147, "time": 11965.88, "timesteps": 489884, "cpu_memory": 9.75, "cpu_percent": 32.4, "learning_rate": 0.00025, "loss_mean": 0.23, "n_updates": 48}, {"reward": 330, "eps": 0.2, "len": 122, "time": 11969.29, "timesteps": 490006, "cpu_memory": 9.75, "cpu_percent": 32.4, "learning_rate": 0.00025, "loss_mean": 0.23, "n_updates": 49}, {"reward": 440, "eps": 0.2, "len": 134, "time": 11972.73, "timesteps": 490140, "cpu_memory": 9.76, "cpu_percent": 32.4, "learning_rate": 0.00025, "loss_mean": 0.21, "n_updates": 49}, {"reward": 520, "eps": 0.2, "len": 137, "time": 11976.28, "timesteps": 490277, "cpu_memory": 9.76, "cpu_percent": 32.4, "learning_rate": 0.00025, "loss_mean": 0.22, "n_updates": 49}, {"reward": 440, "eps": 0.2, "len": 148, "time": 11980.11, "timesteps": 490425, "cpu_memory": 9.76, "cpu_percent": 32.5, "learning_rate": 0.00025, "loss_mean": 0.23, "n_updates": 49}, {"reward": 480, "eps": 0.2, "len": 191, "time": 11985.07, "timesteps": 490616, "cpu_memory": 9.76, "cpu_percent": 32.5, "learning_rate": 0.00025, "loss_mean": 0.21, "n_updates": 49}, {"reward": 700, "eps": 0.2, "len": 244, "time": 11991.33, "timesteps": 490860, "cpu_memory": 9.76, "cpu_percent": 32.4, "learning_rate": 0.00025, "loss_mean": 0.21, "n_updates": 49}, {"reward": 390, "eps": 0.2, "len": 178, "time": 11995.74, "timesteps": 491038, "cpu_memory": 9.76, "cpu_percent": 32.4, "learning_rate": 0.00025, "loss_mean": 0.22, "n_updates": 49}, {"reward": 550, "eps": 0.2, "len": 149, "time": 11999.51, "timesteps": 491187, "cpu_memory": 9.76, "cpu_percent": 32.4, "learning_rate": 0.00025, "loss_mean": 0.22, "n_updates": 49}, {"reward": 710, "eps": 0.2, "len": 163, "time": 12003.65, "timesteps": 491350, "cpu_memory": 9.76, "cpu_percent": 32.5, "learning_rate": 0.00025, "loss_mean": 0.23, "n_updates": 49}, {"reward": 630, "eps": 0.2, "len": 201, "time": 12008.91, "timesteps": 491551, "cpu_memory": 9.77, "cpu_percent": 32.5, "learning_rate": 0.00025, "loss_mean": 0.22, "n_updates": 49}, {"reward": 620, "eps": 0.2, "len": 203, "time": 12014.06, "timesteps": 491754, "cpu_memory": 9.77, "cpu_percent": 32.5, "learning_rate": 0.00025, "loss_mean": 0.22, "n_updates": 49}, {"reward": 430, "eps": 0.2, "len": 161, "time": 12018.09, "timesteps": 491915, "cpu_memory": 9.77, "cpu_percent": 32.5, "learning_rate": 0.00025, "loss_mean": 0.2, "n_updates": 49}, {"reward": 660, "eps": 0.2, "len": 202, "time": 12023.19, "timesteps": 492117, "cpu_memory": 9.77, "cpu_percent": 32.5, "learning_rate": 0.00025, "loss_mean": 0.23, "n_updates": 49}, {"reward": 610, "eps": 0.2, "len": 210, "time": 12028.53, "timesteps": 492327, "cpu_memory": 9.77, "cpu_percent": 32.5, "learning_rate": 0.00025, "loss_mean": 0.23, "n_updates": 49}, {"reward": 360, "eps": 0.2, "len": 122, "time": 12031.66, "timesteps": 492449, "cpu_memory": 9.77, "cpu_percent": 32.5, "learning_rate": 0.00025, "loss_mean": 0.21, "n_updates": 49}, {"reward": 130, "eps": 0.2, "len": 110, "time": 12034.45, "timesteps": 492559, "cpu_memory": 9.77, "cpu_percent": 32.5, "learning_rate": 0.00025, "loss_mean": 0.21, "n_updates": 49}, {"reward": 670, "eps": 0.2, "len": 236, "time": 12040.57, "timesteps": 492795, "cpu_memory": 9.77, "cpu_percent": 32.5, "learning_rate": 0.00025, "loss_mean": 0.22, "n_updates": 49}]